Workbook

Sheet Synthèse
A1: Mise en données des matériaux — synthèse
A2: D'où viennent les proportions portées dans data/mixtures/*.xml : hypothèses, étapes et formules, un onglet par matériau
A3: Fichier(s) XML : data/mixtures/ — 12 matériaux, 21 fichiers de mélange
A5: §1 — MODE D'EMPLOI
B6: Chaque onglet matériau reconstruit, ÉTAPE PAR ÉTAPE ET EN FORMULES VIVANTES, la chaîne qui mène de la donnée expérimentale publiée aux trois nombres portés dans le fichier XML. Modifier une cellule bleue (donnée d'entrée) recalcule toute la chaîne jusqu'à la composition, et jusqu'à l'écart affiché avec la valeur réellement présente dans le dépôt.
B7: Trame commune à tous les onglets : §0 fiche d'identité · §1 hypothèses · §2 données d'entrée (avec sources) · §3 calcul pas à pas · §4 résultat porté dans le XML · §5 contrôles et validation croisée · §6 sensibilité · §7 réponse matériau (hors XML) · §8 bloc XML.
B8: L'onglet Constantes porte les masses molaires, l'air de couche limite, les motifs de résine et le rappel du bilan de masse de surface — il est référencé par tous les autres.
A10: §2 — TABLEAU DE SYNTHÈSE : LES COMPOSITIONS DES XML
B11: Matériau (onglet) | C11: gaz — C | D11: gaz — H | E11: gaz — O | F11: H/O | G11: char | H11: k = B'g/B'c
B12: TACOT | C12: ='TACOT'!C73 -> 0.206 | D12: ='TACOT'!D73 -> 0.679 | E12: ='TACOT'!E73 -> 0.115 | F12: ='TACOT'!D73/'TACOT'!E73 -> 5.9043478 | G12: C:1.0 | H12: ='TACOT'!C103 -> 0.27272727
B13: CPh70 | C13: ='CPh70'!C48 -> 0.206 | D13: ='CPh70'!D48 -> 0.679 | E13: ='CPh70'!E48 -> 0.115 | F13: ='CPh70'!D48/'CPh70'!E48 -> 5.9043478 | G13: C:1.0 | H13: ='CPh70'!C43 -> 0.13846154
B14: ZURAM 18/50 | C14: ='ZURAM'!C59 -> 0.171 | D14: ='ZURAM'!D59 -> 0.722 | E14: ='ZURAM'!E59 -> 0.107 | F14: ='ZURAM'!D59/'ZURAM'!E59 -> 6.7476636 | G14: C:1.0 | H14: ='ZURAM'!C106 -> 0.24101132
B15: SC-1008 (PICA) | C15: ='SC-1008'!C55 -> 0.2526 | D15: ='SC-1008'!D55 -> 0.6407 | E15: ='SC-1008'!E55 -> 0.1068 | F15: ='SC-1008'!D55/'SC-1008'!E55 -> 5.9990637 | G15: C:1.0 | H15: ='SC-1008'!C126 -> 0.2345679
B16: MX-4926 | C16: ='MX-4926'!C68 -> 0.2526 | D16: ='MX-4926'!D68 -> 0.6407 | E16: ='MX-4926'!E68 -> 0.1068 | F16: ='MX-4926'!D68/'MX-4926'!E68 -> 5.9990637 | G16: C:1.0 | H16: ='MX-4926'!C56 -> 0.1816839
B17: Liège/phénolique | C17: ='Liège-phénolique'!C80 -> 0.287 | D17: ='Liège-phénolique'!D80 -> 0.592 | E17: ='Liège-phénolique'!E80 -> 0.121 | F17: ='Liège-phénolique'!D80/'Liège-phénolique'!E80 -> 4.892562 | G17: C:1.0 | H17: ='Liège-phénolique'!C120 -> 4
B18: Bois de chêne | C18: ='Chêne'!C67 -> 0.221 | D18: ='Chêne'!D67 -> 0.536 | E18: ='Chêne'!E67 -> 0.243 | F18: ='Chêne'!D67/'Chêne'!E67 -> 2.2057613 | G18: C:1.0 | H18: ='Chêne'!C106 -> 4
B19: Carbone graphite | C19: — | D19: — | E19: — | F19: — | G19: C:1.0 | H19: ='Carbone'!C53 -> 0
B20: Silice SiO2 | C20: — | D20: — | E20: — | F20: — | G20: Si:1.0, O:2.0 | H20: ='Silice'!C46 -> 0
B21: Carbure de silicium SiC | C21: — | D21: — | E21: — | F21: — | G21: Si:1.0, C:1.0 | H21: ='SiC'!C69 -> 0
B22: Molybdène (TZM) | C22: — | D22: — | E22: — | F22: — | G22: Mo:1.0 | H22: ='Molybdène'!C53 -> 0
B23: Les colonnes « gaz » sont des liens vers la ligne « valeur portée dans le XML » de chaque onglet. Le graphite, la silice, le SiC et le molybdène n'ont pas de gaz de pyrolyse (k = 0). TACOT et CPh70 portent RIGOUREUSEMENT la même composition : leurs fichiers XML sont identiques, seul k les distingue — c'est la démonstration de l'onglet CPh70.
A25: §3 — LES TROIS SEULES DONNÉES QUE CONSOMME LE CALCUL
B26: # | C26: Composition | D26: Rôle dans le bilan | E26: Option | F26: Comment on l'obtient
B27: 1 | C27: bord de couche limite | D27: Y_e | E27: -bl | F27: l'atmosphère : air N:0.79 O:0.21 · Mars · Titan…
B28: 2 | C28: gaz de pyrolyse | D28: Y_g | E28: -py | F28: c'est TOUT l'objet de ce classeur — quatre routes possibles, §4
B29: 3 | C29: char | D29: Y_c | E29: -char + -char-elem | F29: C:1.0 si tous les constituants carbonisent vers le carbone ; sinon pondérer par les masses de char
B30: Plus T, P et B'g. Rien d'autre : cf. src/apps/bprime.cpp:304-330. Sans -char/-char-elem, bprime utilise un char de carbone pur intégré ; les deux options vont toujours ensemble.
A32: §4 — LES QUATRE ROUTES DE CALCUL DU GAZ DE PYROLYSE
B33: Route | C33: Matériau | D33: Donnée primaire | E33: Passage à l'élémentaire | F33: Point critique
B34: A — sommation atomique | C34: TACOT, CPh70 | D34: spéciation moléculaire mesurée (7 espèces) | E34: n_E = Σ_j ν_E,j · x_j | F34: la renormalisation : somme réelle des colonnes (100.30), pas les totaux imprimés (100.0)
B35: B — conversion directe | C35: ZURAM | D35: composition élémentaire MASSIQUE mesurée | E35: x_E = (y_E/M_E) / Σ (y_j/M_j) | F35: traçabilité limitée à 3 décimales ; la source primaire VKI n'est pas publique
B36: C — fermeture élémentaire | C36: SC-1008, Chêne | D36: motif idéalisé (SC-1008) ou analyse élémentaire (chêne) + rendement en char | E36: n_E(gaz) = n_E(solide) − n_E(char) | F36: le rendement en char entre DANS la chaîne : ±0.05 sur Y déplace le carbone de ~12 %
B37: D — fermeture sur DEUX constituants | C37: Liège/phénolique | D37: analyses des deux constituants + rendements | E37: n_E(gaz) = Σ_i [n_E(i) − n_E(char,i)] | F37: le renfort pyrolyse : le rapport renfort/résine entre dans la table B'
B38: E — stœchiométrie directe | C38: Carbone, Silice, SiC, Mo | D38: la formule du solide | E38: aucun gaz de pyrolyse (B'g = 0) | F38: le char EST le matériau ; -char-elem Si pour la silice, N pour le SiC (char non congruent)
A40: §5 — CE QUI N'ENTRE PAS DANS LE XML
B41: Donnée | C41: Dans le XML ? | D41: Où elle sert vraiment
B42: masse volumique ρ_v, ρ_c | C42: non | D42: solveur de réponse matériau ; récession ṡ = B'c·ṁe/ρ_c
B43: porosité | C43: non | D43: conduction, perméabilité
B44: rapport fibres/résine | C44: non * | D44: fixe la QUANTITÉ de gaz (donc B'g), pas sa composition
B45: rendement en char | C45: non * | D45: idem — mais il entre dans le CALCUL du gaz pour les routes C et D
B46: cinétique de pyrolyse | C46: non | D46: fixe B'g au cours du temps
B47: * sauf si les constituants donnent des chars de compositions élémentaires DIFFÉRENTES (fibres de silice + résine phénolique), ou si le renfort pyrolyse (liège) : le rapport entre alors dans Y_c et/ou Y_g, et la table change. Le bilan de masse de surface est écrit sur des fractions massiques élémentaires, donc normalisées : les grandeurs VOLUMIQUES n'y ont structurellement aucune place.
A49: §6 — RECETTE POUR UN NOUVEAU MATÉRIAU
A50: 1 | B50: Atmosphère → composition -bl (air, Mars, Titan…).
A51: 2 | B51: Résine → composition du gaz de pyrolyse par l'une des quatre routes du §4 → composition -py.
A52: 3 | B52: Char → C:1.0 si tous les constituants carbonisent vers le carbone ; sinon pondérer par les masses de char de chaque constituant.
A53: 4 | B53: Espèces → tous les produits attendus des éléments présents, PLUS la ou les phases condensées.
A54: 5 | B54: Vérifier : checkmix (noms, phases), puis un run court.
A55: 6 | B55: Contrôler la physique : à 300 K et B'g = 0 dans l'air, un char carboné doit donner B'c ≈ 0.0874 (limite C + O2 → CO2, indépendante de la pression). Une valeur ≈ 200 signale l'absence de C(gr). Pour un char multi-élément susceptible de laisser un autre solide à la paroi (SiC), suivre le bilan sur N (-char-elem N).
B57: Documents de référence du dépôt : tacot_bprime/mise_en_donnees_xml.md (mécanique du fichier XML et règles du parseur) · resine_tacot.md · zuram_bprime/resine_zuram.md · sc1008_bprime/resine_sc1008.md · cork_bprime/mise_en_donnees_cork.md · oak_bprime/mise_en_donnees_chene.md · tacot_bprime/cph70_vs_tacot.md · carbon_bprime/bprime_carbon_physique.md · sic_bprime/README.md · mo_bprime/README.md.

Sheet Constantes
A1: Constantes et conventions communes
A2: Masses molaires, air de couche limite, motifs de résine, bilan de masse de surface — référencés par tous les onglets matériaux
A3: Fichier(s) XML : toutes les mises en données de data/mixtures/
A5: §1 — MASSES MOLAIRES DES ÉLÉMENTS
B6: Élément | C6: M usuelle [g/mol] | D6: M classeur ZURAM [g/mol]
B7: Carbone C | C7: 12.011 | D7: 12.0107
B8: Hydrogène H | C8: 1.008 | D8: 1.00794
B9: Oxygène O | C9: 15.999 | D9: 15.999
B10: Azote N | C10: 14.007 | D10: —
B11: Silicium Si | C11: 28.0855 | D11: —
B12: Colonne « usuelle » : valeurs employées par les scripts du dépôt (cork_pyrolysis_data.py). Colonne « classeur ZURAM » : valeurs de Tacot_Zuram_Calcarb_database_v4.3.1.ods, onglet ZURAM_official!F87:F89 — elles seules reproduisent les fractions molaires de ce classeur au 1e-16 près.
A14: §2 — BORD DE COUCHE LIMITE : L'AIR (identique dans tous les XML)
B15: Air (option -bl) | C15: N | D15: O | E15: Somme
B16: fraction molaire élémentaire x_E (XML) | C16: 0.79 | D16: 0.21 | E16: =SUM(C16:D16) -> 1
B17: masse molaire M_E [g/mol] | C17: =Constantes!$C$10 -> 14.007 | D17: =Constantes!$C$9 -> 15.999
B18: x_E · M_E | C18: =C16*C17 -> 11.06553 | D18: =D16*D17 -> 3.35979 | E18: =SUM(C18:D18) -> 14.42532
B19: fraction massique élémentaire y_E | C19: =C18/$E$18 -> 0.76709078 | D19: =D18/$E$18 -> 0.23290922 | E19: =SUM(C19:D19) -> 1
B20: y_E = x_E·M_E / Σ x_j·M_j. Le parseur de Mutation++ normalise seul la somme à 1 et convertit mole ↔ masse (Mixture.cpp:131-138) : `type="mole"` est le défaut, `type="mass"` doit être déclaré explicitement si la source est massique.
A22: §3 — MOTIFS DE RÉSINE PHÉNOLIQUE (référence commune TACOT / ZURAM / SC-1008 / liège)
A23: > | B23: Un motif cuit s'écrit C(6+b)H6O : un cycle phénolique et b ponts méthylène –CH2–. | I23: M = ν_C·M_C + ν_H·M_H + ν_O·M_O ; w_E = ν_E·M_E / M
B24: Motif | C24: ν_C | D24: ν_H | E24: ν_O | F24: % C masse | G24: % H masse | H24: % O masse
B25: phénol C6H6O (monomère) | C25: 6 | D25: 6 | E25: 1 | F25: =C25*Constantes!$C$7/(C25*Constantes!$C$7+D25*Constantes!$C$8+E25*Constantes!$C$9)*100 -> 76.573906 | G25: =D25*Constantes!$C$8/(C25*Constantes!$C$7+D25*Constantes!$C$8+E25*Constantes!$C$9)*100 -> 6.4263173 | H25: =E25*Constantes!$C$9/(C25*Constantes!$C$7+D25*Constantes!$C$8+E25*Constantes!$C$9)*100 -> 16.999777 | I25: TACOT : motif équivalent mesuré (Sykes table II), à 0.85 point près
B26: novolac linéaire C7H6O (b = 1) | C26: 7 | D26: 6 | E26: 1 | F26: =C26*Constantes!$C$7/(C26*Constantes!$C$7+D26*Constantes!$C$8+E26*Constantes!$C$9)*100 -> 79.225246 | G26: =D26*Constantes!$C$8/(C26*Constantes!$C$7+D26*Constantes!$C$8+E26*Constantes!$C$9)*100 -> 5.6989936 | H26: =E26*Constantes!$C$9/(C26*Constantes!$C$7+D26*Constantes!$C$8+E26*Constantes!$C$9)*100 -> 15.07576 | I26: ZURAM : motif équivalent mesuré ([THo] fig. 7), à 0.35 point près ; liège : motif retenu pour la résine
B27: résol saturé / réticulé C7.5H6O (b = 1.5) | C27: 7.5 | D27: 6 | E27: 1 | F27: =C27*Constantes!$C$7/(C27*Constantes!$C$7+D27*Constantes!$C$8+E27*Constantes!$C$9)*100 -> 80.337913 | G27: =D27*Constantes!$C$8/(C27*Constantes!$C$7+D27*Constantes!$C$8+E27*Constantes!$C$9)*100 -> 5.3937635 | H27: =E27*Constantes!$C$9/(C27*Constantes!$C$7+D27*Constantes!$C$8+E27*Constantes!$C$9)*100 -> 14.268324 | I27: SC-1008 : motif RETENU (résol saturé) — M = 112.13 g/mol
B28: Le nombre de ponts b n'est pas un réglage libre : le phénol a 3 sites réactifs (2 ortho + 1 para) et un pont est partagé entre 2 cycles, d'où b ≤ 1.5 à réseau saturé. Novolac (formé en défaut de formaldéhyde, durci à l'hexamine) et résol (excès de formaldéhyde, auto-réticulant) glissent sur la MÊME courbe : seul b diffère. L'analyse élémentaire C/H/O ne permet donc pas de distinguer les deux — seul l'azote le fait.
A30: §4 — LE BILAN QUI CONSOMME CES COMPOSITIONS (rappel)
B31: Bilan de conservation de chaque élément i à la paroi, couche limite laminaire à nombre de Lewis unité :
B32: (1 + B'c + B'g) · Y_w,i = Y_e,i + B'c · Y_c,i + B'g · Y_g,i
B34: => B'c = [ Y_e,i + B'g·Y_g,i − Y_w,i·(1 + B'g) ] / ( Y_w,i − Y_c,i )
B35: Y_e = bord de couche limite (option -bl) · Y_g = gaz de pyrolyse (-py) · Y_c = char (-char, avec -char-elem) · Y_w = gaz à la paroi, calculé à l'équilibre thermochimique à (T_w, P). `bprime` ne consomme QUE ces trois compositions élémentaires, plus T, P et B'g (src/apps/bprime.cpp:304-330).
B36: Conséquence majeure : aucune grandeur volumique (masse volumique, porosité, rapport fibres/résine, rendement en char, cinétique) n'entre dans le XML. Toutes vivent dans le solveur de réponse matériau — voir le §7 de chaque onglet.
A38: §5 — LÉGENDE DES COULEURS ET MODE D'EMPLOI
B39: bleu — donnée d'entrée en dur : mesure, valeur publiée, hypothèse. C'est ici qu'on édite.
B40: noir — cellule calculée par formule vivante. Ne pas écraser.
B41: vert — lien vers un autre onglet (constantes, ou composition héritée d'un autre matériau).
B42: rouge sur fond rosé — la valeur telle qu'elle figure dans le fichier XML du dépôt.
B43: fond jaune — hypothèse clé : c'est le paramètre dont dépend le plus le résultat.
B45: Chaque onglet matériau suit la même trame : §0 fiche d'identité · §1 hypothèses · §2 données d'entrée · §3 calcul pas à pas · §4 résultat porté dans le XML · §5 contrôles et validation croisée · §6 sensibilité · §7 réponse matériau (hors XML) · §8 bloc XML.

Sheet TACOT
A1: TACOT — Theoretical Ablative Composite for Open Testing
A2: Carbone/phénolique poreux · gaz de pyrolyse obtenu par SOMMATION ATOMIQUE d'une spéciation moléculaire mesurée
A3: Fichier(s) XML : data/mixtures/tacot-air_25.xml · tacot-air_35.xml · tacot-pyrogas.xml
A5: §0 — FICHE D'IDENTITÉ
B6: Matériau | C6: TACOT 3.0 (matériau de référence ouvert) | I6: Classeur TACOT_3.0.xls, onglet Description
B7: Renfort | C7: fibres de carbone ex-cellulose, traitées à 2000 K, 1600 kg/m³ | I7: Description!A11 — « The carbon fibers do not pyrolyse » ('Pyrolysis model'!H20)
B8: Résine | C8: novolac phénol-formaldéhyde Union Carbide BRP 5549 + hexamine (HMTA), 1200 kg/m³ | I8: Sykes, NASA TN D-3810 (1967), § MATERIAL p. 2 ; Description!A12
B9: Microstructure | C9: ε_fibres 0.10 / ε_matrice 0.10 / porosité 0.80 | I9: Description!A15:A17
B10: Source primaire du gaz | C10: Sykes, table I (chromatographie, paliers de 50 °C entre 100 et 1000 °C) | I10: reprise dans 'Pyrolysis-gas chemistry'!B5:H5 puis 'Pyrolysis model'!B4:B6
B11: Compositions du XML | C11: air (-bl) · tacot_pyro (-py) · tacot_char (-char, -char-elem C) | I11: tacot_bprime/resine_tacot.md et mise_en_donnees_xml.md
A13: §1 — HYPOTHÈSES
A14: H1 | B14: Le gaz de pyrolyse est produit par la RÉSINE SEULE. | I14: Les fibres ex-cellulose sont déjà traitées à 2000 K : elles ne pyrolysent pas ('Pyrolysis model'!H20). Le rapport fibres/résine ne fixe donc que la QUANTITÉ de gaz (donc B'g), pas sa composition — cf. onglet CPh70.
A15: H2 | B15: La spéciation retenue est la somme RÉELLE des colonnes de la table I de Sykes (100.30), pas les totaux imprimés arrondis (100.0). | I15: C'est ce choix, et lui seul, qui permet de reproduire le classeur TACOT 3.0 au 1e-16 près (§5).
A16: H3 | B16: Réduction du modèle : toluène C7H8 → benzène C6H6, et 2,4-xylénol C8H10O → phénol C6H5OH. | I16: 'Pyrolysis-gas chemistry'!A8 : compatibilité avec le mécanisme cinétique d'April (10 réactions), qui ignore toluène et xylénol. Conservative en atomes à ~1 % près (C7H8→C6H6 perd un CH2).
A17: H4 | B17: Le gaz est déclaré SANS AZOTE. | I17: Les 2.35 % de N de la résine viennent de la HMTA prémélangée ; ils s'effondrent à 0.42 % dès 400 °C et à zéro à 500 °C (Sykes table II) : signature d'un composé piégé, pas d'un azote de structure.
A18: H5 | B18: Le char est du carbone pur : C:1.0. | I18: Sykes mesure pourtant C 92.65 / H 0.90 / O 6.45 % à 850 °C. L'hypothèse reste licite en ablation : la paroi dépasse 2000 K (l'oxygène résiduel part en CO bien avant) et les fibres, 57 % de la masse vierge, sont déjà du carbone pur.
A19: H6 | B19: Le gaz à la paroi est à l'équilibre thermochimique à (T_w, P). | I19: Hypothèse centrale de la table B'. Le solveur multiphase de Mutation++ traite la coexistence gaz / C(gr).
A20: H7 | B20: Liste d'espèces = les 25 espèces gazeuses de la table B' de référence, PLUS la phase condensée C(gr). | I20: Sans C(gr) l'excès de carbone ne peut pas se condenser : Y_w,C → 1 et B'c sature vers ≈ 200 au lieu de ≈ 0.087 à 300 K. La liste conditionne le résultat : 25 espèces donnent 0.43 % d'écart moyen contre la table de référence, 35 espèces 2.41 %.
A22: §2 — DONNÉES D'ENTRÉE
A23: > | B23: Table I de Sykes — distribution des produits de décomposition, en % des moles totales observées | I23: somme sur les 19 paliers de température
B24: Espèce (table I) | C24: Σ colonne (réelle) | D24: total imprimé | E24: après réduction H3
B25: CO2 | C25: 1.57 | D25: 1.6 | E25: CO2
B26: CO | C26: 5.78 | D26: 5.5 | E26: CO
B27: C6H6 benzène | C27: 0.17 | D27: 0.2 | E27: C6H6
B28: C7H8 toluène | C28: 0.31 | D28: 0.3 | E28: → C6H6
B29: C6H5OH phénol | C29: 7.14 | D29: 7.1 | E29: C6H5OH
B30: (CH3)2C6H3OH xylénol | C30: 1.8 | D30: 1.8 | E30: → C6H5OH
B31: CH4 | C31: 10.03 | D31: 10 | E31: CH4
B32: H2O | C32: 23.43 | D32: 23.4 | E32: H2O
B33: H2 | C33: 50.07 | D33: 50.1 | E33: H2
B34: SOMME | C34: =SUM(C25:C33) -> 100.3 | D34: =SUM(D25:D33) -> 100 | E34: ← 100.30 contre 100.0 : voir H2
B35: Les totaux imprimés au bas de la table de Sykes sont arrondis et somment à 100.0 ; les colonnes elles-mêmes somment à 100.30. C'est cette dernière valeur que le classeur TACOT 3.0 utilise pour renormaliser.
B37: Analyse élémentaire de la résine vierge — C [% masse] | C37: 75.6 | I37: Sykes, table II, ligne « ambiant ». L'analyse ne dose que C, H et N ; O est le complément à 100 % (cendres mesurées à 0.04 %, négligeables).
B38: H [% masse] | C38: 6.12
B39: N [% masse] | C39: 2.35 | I39: issu de la HMTA — retiré du gaz, cf. H4
B40: O [% masse] | C40: 15.93 | I40: complément à 100 %
B41: Rendement en char de la résine — mesuré | C41: 0.54 | I41: Sykes table II : fraction massique résiduelle à 850 °C
B42: Rendement en char de la résine — modèle TACOT | C42: 0.5 | I42: implicite : microstructure ('Pyrolysis model'!A32:A34) ET cinétique de Goldstein (B18:C19) donnent 0.50 toutes deux
B43: ρ fibres / ρ résine [kg/m³] | C43: 1600 | I43: Description!A11
C44: 1200 | I44: Description!A12
B45: ε_fibres / ε_matrice [-] | C45: 0.1 | I45: Description!A15:A17 (porosité 0.80)
C46: 0.1
A48: §3 — CALCUL PAS À PAS
A49: > | B49: Étape 1 — regrouper les 9 espèces de Sykes en 7 (réduction H3), puis renormaliser par la somme réelle | I49: x_j = n_j / Σ n_j avec Σ n_j = 100.30
B50: Espèce du modèle | C50: moles brutes | D50: x_j calculé | E50: classeur TACOT 3.0 | F50: ν_C | G50: ν_H | H50: ν_O
B51: CO2 | C51: =C25 -> 1.57 | D51: =C51/$C$34 -> 0.015653041 | E51: 0.015653041 | F51: 1 | G51: 0 | H51: 2
B52: CO | C52: =C26 -> 5.78 | D52: =C52/$C$34 -> 0.057627119 | E52: 0.057627119 | F52: 1 | G52: 0 | H52: 1
B53: C6H6 | C53: =C27+C28 -> 0.48 | D53: =C53/$C$34 -> 0.0047856431 | E53: 0.0047856431 | F53: 6 | G53: 6 | H53: 0
B54: C6H5OH | C54: =C29+C30 -> 8.94 | D54: =C54/$C$34 -> 0.089132602 | E54: 0.089132602 | F54: 6 | G54: 6 | H54: 1
B55: CH4 | C55: =C31 -> 10.03 | D55: =C55/$C$34 -> 0.1 | E55: 0.1 | F55: 1 | G55: 4 | H55: 0
B56: H2O | C56: =C32 -> 23.43 | D56: =C56/$C$34 -> 0.2335992 | E56: 0.2335992 | F56: 0 | G56: 2 | H56: 1
B57: H2 | C57: =C33 -> 50.07 | D57: =C57/$C$34 -> 0.49920239 | E57: 0.49920239 | F57: 0 | G57: 2 | H57: 0
B58: SOMME | C58: =SUM(C51:C57) -> 100.3 | D58: =SUM(D51:D57) -> 1 | E58: =SUM(E51:E57) -> 1
B59: écart maximal au classeur, espèce par espèce | C59: =MAX(ABS(D51-E51),ABS(D52-E52),ABS(D53-E53),ABS(D54-E54),ABS(D55-E55),ABS(D56-E56),ABS(D57-E57)) -> 4.7184479e-16 | I59: Colonne « classeur TACOT 3.0 » : 'Pyrolysis-gas chemistry'!B5:H5. Attendu ~5e-16, la précision de la double précision : la chaîne Sykes → classeur est entièrement élucidée.
A61: > | B61: Étape 2 — sommation atomique : passer du moléculaire à l'élémentaire | I61: n_E = Σ_j ν_E,j · x_j (SOMMEPROD)
B62: Moles d'atomes par mole de gaz | C62: C | D62: H | E62: O | F62: Somme
B63: n_E = Σ_j ν_E,j · x_j | C63: =SUMPRODUCT($D$51:$D$57,F51:F57) -> 0.73678963 | D63: =SUMPRODUCT($D$51:$D$57,G51:G57) -> 2.4291127 | E63: =SUMPRODUCT($D$51:$D$57,H51:H57) -> 0.411665 | F63: =SUM(C63:E63) -> 3.5775673
A64: > | B64: Étape 3 — normaliser en fractions molaires élémentaires, puis convertir en fractions massiques | I64: x_E = n_E / Σ n_j ; M_gaz = Σ x_E·M_E ; y_E = x_E·M_E / M_gaz
C65: C | D65: H | E65: O | F65: Somme | G65: M_gaz [g/mol]
B66: x_E (fraction molaire élémentaire) | C66: =C63/$F$63 -> 0.20594711 | D66: =D63/$F$63 -> 0.67898448 | E66: =E63/$F$63 -> 0.11506842 | F66: =SUM(C66:E66) -> 1 | G66: =C66*Constantes!$C$7+D66*Constantes!$C$8+E66*Constantes!$C$9 -> 4.9990266
B67: y_E (fraction massique élémentaire) | C67: =C66*Constantes!$C$7/$G$66 -> 0.49482247 | D67: =D66*Constantes!$C$8/$G$66 -> 0.13690992 | E67: =E66*Constantes!$C$9/$G$66 -> 0.36826761 | F67: =SUM(C67:E67) -> 1
B68: M_gaz ≈ 5.0 g/mol : un gaz très léger, dominé par H2 (50 % des moles). En masse le gaz est pourtant à ~49 % de carbone.
A70: §4 — RÉSULTAT : CE QUI ENTRE DANS LE XML
B71: Composition élémentaire (fractions molaires) | C71: C | D71: H | E71: O | F71: Somme
B72: calcul — chaîne complète ci-dessus | C72: =C66 -> 0.20594711 | D72: =D66 -> 0.67898448 | E72: =E66 -> 0.11506842 | F72: =SUM(C72:E72) -> 1
B73: valeur portée dans le XML (tacot_pyro) | C73: 0.206 | D73: 0.679 | E73: 0.115 | F73: =SUM(C73:E73) -> 1
B74: écart relatif |calcul − XML| / XML | C74: =ABS(C72-C73)/C73 -> 0.00025676761 | D74: =ABS(D72-D73)/D73 -> 2.2861076e-05 | E74: =ABS(E72-E73)/E73 -> 0.00059492869
B75: L'écart est celui de l'arrondi à trois décimales opéré en 'Pyrolysis model'!B4:B6. Mutation++ normalise la somme à 1 : porter C:0.7368, H:2.4291, O:0.4117 (les moles brutes) donnerait rigoureusement le même mélange.
B77: Char (tacot_char) | C77: C | D77: H | E77: O
B78: composition du XML | C78: 1 | D78: — | E78: —
B79: Fibres de carbone et résine carbonisée donnent toutes deux du carbone pur : C:1.0 quel que soit le rapport fibres/résine (cf. H5). Option `-char-elem C`.
A81: §5 — CONTRÔLES ET VALIDATION CROISÉE
A82: > | B82: Contrôle A — reproduction du classeur TACOT 3.0 : écart maximal sur les 7 fractions molaires | I82: cf. colonne F de l'étape 1
B83: écart maximal espèce par espèce | C83: =C59 -> 4.7184479e-16 | I83: reporté de l'étape 1 — attendu ≈ 5e-16 (double précision)
A84: > | B84: Contrôle B — fermeture inverse INDÉPENDANTE : partir de la résine mesurée (table II), retrancher un char de carbone pur, comparer au gaz de la table I | I84: n_E(gaz) = n_E(résine) − n_E(char) ; n_C(char) = Y·100 / M_C
B85: Base 100 g de résine vierge | C85: C | D85: H | E85: O | F85: Somme | G85: écart max / table I
B86: moles d'atomes de la résine (table II) | C86: =C37/Constantes!$C$7 -> 6.2942303 | D86: =C38/Constantes!$C$8 -> 6.0714286 | E86: =C40/Constantes!$C$9 -> 0.99568723 | F86: =SUM(C86:E86) -> 13.361346
B87: char retranché, Y = 0.540 (mesuré) | C87: =$C$41*100/Constantes!$C$7 -> 4.4958788 | D87: 0 | E87: 0
B88: gaz obtenu — x_E | C88: =(C86-C87)/($F$86-$C$87) -> 0.20284904 | D88: =(D86-D87)/($F$86-$C$87) -> 0.68484022 | E88: =(E86-E87)/($F$86-$C$87) -> 0.11231074 | F88: =SUM(C88:E88) -> 1 | G88: =MAX(ABS(C88-C72)/C72,ABS(D88-D72)/D72,ABS(E88-E72)/E72) -> 0.023965505
B89: Accord à 2.4 % entre DEUX TECHNIQUES EXPÉRIMENTALES INDÉPENDANTES : analyse élémentaire du résidu (DTA, table II) d'un côté, chromatographie des effluents (table I) de l'autre. C'est la validation la plus forte de la cohérence interne de Sykes — et, accessoirement, du fait que le char soit assimilable à du carbone pur.
A91: §6 — SENSIBILITÉ AU RENDEMENT EN CHAR
B92: Rendement en char Y | C92: C | D92: H | E92: O | F92: écart max / table I | G92: origine de la valeur
B93: 0.5 | C93: =(($C$86-B93*100/Constantes!$C$7))/($F$86-B93*100/Constantes!$C$7) -> 0.23170959 | D93: =$D$86/($F$86-B93*100/Constantes!$C$7) -> 0.66004584 | E93: =$E$86/($F$86-B93*100/Constantes!$C$7) -> 0.10824458 | F93: =MAX(ABS(C93-$C$72)/$C$72,ABS(D93-$D$72)/$D$72,ABS(E93-$E$72)/$E$72) -> 0.12509271 | G93: modèle TACOT : microstructure + cinétique de Goldstein
B94: 0.534 | C94: =(($C$86-B94*100/Constantes!$C$7))/($F$86-B94*100/Constantes!$C$7) -> 0.20731557 | D94: =$D$86/($F$86-B94*100/Constantes!$C$7) -> 0.68100297 | E94: =$E$86/($F$86-B94*100/Constantes!$C$7) -> 0.11168145 | F94: =MAX(ABS(C94-$C$72)/$C$72,ABS(D94-$D$72)/$D$72,ABS(E94-$E$72)/$E$72) -> 0.029434347 | G94: ajustement optimal (moindre écart)
B95: 0.54 | C95: =(($C$86-B95*100/Constantes!$C$7))/($F$86-B95*100/Constantes!$C$7) -> 0.20284904 | D95: =$D$86/($F$86-B95*100/Constantes!$C$7) -> 0.68484022 | E95: =$E$86/($F$86-B95*100/Constantes!$C$7) -> 0.11231074 | F95: =MAX(ABS(C95-$C$72)/$C$72,ABS(D95-$D$72)/$D$72,ABS(E95-$E$72)/$E$72) -> 0.023965505 | G95: Sykes table II — mesuré à 850 °C
B96: Le rendement en char n'entre PAS dans le calcul du gaz du XML : celui-ci vient directement de la table I. Ce tableau ne sert qu'au contrôle croisé — et il montre que le 0.50 du modèle TACOT est une valeur arrondie pour produire des densités rondes (280/220 kg/m³), pas la mesure (0.540).
A98: §7 — RÉPONSE MATÉRIAU (n'entre PAS dans le XML)
A99: > | B99: Bilan de phase solide et couplage en ablation stationnaire | I99: ρ_v = ε_f·ρ_f + ε_m·ρ_m ; ρ_c = ε_f·ρ_f + Y·ε_m·ρ_m ; k = B'g/B'c = (ρ_v − ρ_c)/ρ_c
B100: ρ vierge [kg/m³] | C100: =$C$45*$C$43+$C$46*$C$44 -> 280 | I100: 'Pyrolysis model'!A32 — attendu 280
B101: ρ char [kg/m³] | C101: =$C$45*$C$43+$C$42*$C$46*$C$44 -> 220 | I101: 'Pyrolysis model'!A33 — attendu 220 (avec Y = 0.50 du modèle)
B102: gaz de pyrolyse libéré [kg/m³] | C102: =C100-C101 -> 60 | I102: soit 21.4 % de la masse vierge
B103: couplage k = B'g / B'c | C103: =(C100-C101)/C101 -> 0.27272727 | I103: point de fonctionnement stationnaire : B'c = B'c_table(T, P, B'g = k·B'c)
B104: k est la SEULE façon dont la microstructure entre dans le résultat final : elle ne change pas la table B'c(T, P, B'g), elle change l'endroit où le matériau la lit. Voir l'onglet CPh70, qui partage la table du TACOT mais pas son k.
A106: §8 — BLOC XML
B107: <mixture thermo_db="NASA-9">
B108: <species>
B109: C H O N CH4 CN CO CO2 C2 C2H C2H2,acetylene C3 C4 C4H2,butadiyne C5
B110: HCN H2 H2O N2 CH2OH CNN CNC CNCOCN C6H6 HNC C(gr)
B111: </species>
B112: <element_compositions default="air">
...

Sheet CPh70
A1: CPh70 — carbone/phénolique dense
A2: Mêmes fibres et même résine que le TACOT, autres proportions · démontre que le rapport fibres/résine N'ENTRE PAS dans le XML
A3: Fichier(s) XML : data/mixtures/cph70-air_25.xml
A5: §0 — FICHE D'IDENTITÉ
B6: Matériau | C6: CPh70 — composite carbone/phénolique dense | I6: 70 % fibres / 30 % résine en volume solide, porosité 0.01
B7: Renfort | C7: fibres de carbone ex-cellulose, 1600 kg/m³ — IDENTIQUES au TACOT | I7: cf. onglet TACOT §0
B8: Résine | C8: novolac/formaldéhyde, 1200 kg/m³ — IDENTIQUE au TACOT | I8: cf. onglet TACOT §0
B9: Source du gaz | C9: héritée du TACOT (résine inchangée) | I9: tacot_bprime/cph70_vs_tacot.md
B10: Compositions du XML | C10: air (-bl) · cph70_pyro (-py) · cph70_char (-char, -char-elem C) | I10: cph70_bprime/README.md
A12: §1 — HYPOTHÈSES
A13: H1 | B13: Fibres et résine RIGOUREUSEMENT identiques à celles du TACOT ; seuls changent les proportions et la porosité. | I13: C'est la définition même du cas d'étude. Si la résine ou la nature des fibres changeait, tout le §3 serait à refaire.
A14: H2 | B14: Le gaz de pyrolyse est produit par la résine seule ⇒ sa composition ÉLÉMENTAIRE est inchangée. | I14: Changer le rapport fibres/résine change la QUANTITÉ de gaz produite (donc B'g), pas sa composition. Or B'g est un paramètre d'ENTRÉE de la table, balayé de 0 à 10.
A15: H3 | B15: Fibres de carbone et résine carbonisée donnent toutes deux du carbone pur ⇒ char C:1.0 quelles que soient les proportions. | I15: La pondération générale n_E(char) = Σ_i (m_char,i/M_i)·ν_E,i se réduit à C:1.0 dès que tous les constituants carbonisent vers le même élément.
A16: H4 | B16: Aucune grandeur volumique n'entre dans le bilan de surface. | I16: Le bilan est écrit sur des fractions massiques élémentaires, donc normalisées : ni ρ, ni porosité, ni ε_f n'y apparaissent (Constantes §4).
A17: H5 | B17: Rendement en char de la résine : 0.50 (valeur du modèle TACOT). | I17: Elle n'entre pas dans le XML — seulement dans ρ_char, donc dans k (§7).
A19: §2 — DONNÉES D'ENTRÉE
B20: fraction volumique de fibres dans le SOLIDE | C20: 0.7 | I20: définition du CPh70
B21: fraction volumique de résine dans le SOLIDE | C21: 0.3 | I21: complément à 1 − 0.70
B22: porosité φ | C22: 0.01 | I22: CPh70 : matériau dense (TACOT : 0.80)
B23: ρ intrinsèque fibres [kg/m³] | C23: 1600 | I23: Description!A11 du classeur TACOT 3.0
B24: ρ intrinsèque résine [kg/m³] | C24: 1200 | I24: Description!A12
B25: rendement en char de la résine | C25: 0.5 | I25: 'Pyrolysis model'!A32:A34 et B18:C19
A27: §3 — CALCUL PAS À PAS
A28: > | B28: Étape 1 — composition du gaz de pyrolyse : elle est HÉRITÉE, pas recalculée | I28: Y_g(CPh70) = Y_g(TACOT), par H1 + H2
B29: Gaz de pyrolyse | C29: C | D29: H | E29: O | F29: Somme
B30: reprise de l'onglet TACOT (chaîne complète : Sykes table I) | C30: ='TACOT'!C66 -> 0.20594711 | D30: ='TACOT'!D66 -> 0.67898448 | E30: ='TACOT'!E66 -> 0.11506842 | F30: =SUM(C30:E30) -> 1
B31: Toute la chaîne de traçabilité du gaz est celle de l'onglet TACOT : table I de Sykes → réduction toluène/xylénol → renormalisation par 100.30 → sommation atomique. Elle n'est PAS refaite ici : la résine est la même, donc le gaz est le même.
A32: > | B32: Étape 2 — char : pondération générale des constituants | I32: n_E(char) = Σ_i (m_char,i / M_i) · ν_E,i
B33: Fibres : carbone pur (ν_C = 1, M = M_C). Résine carbonisée : carbone pur également. La somme pondérée de deux compositions identiques est cette composition, quelles que soient les masses : le char vaut C:1.0 pour TOUT rapport fibres/résine. C'est le point qui rendrait le calcul faux avec des fibres de silice ou un char retenant H/O.
A34: > | B34: Étape 3 — fractions volumiques réelles à partir de la porosité | I34: ε_i = (1 − φ) · f_i
B35: Fractions volumiques | C35: fibres ε_f | D35: résine ε_m | E35: pores φ | F35: Somme
B36: ε = (1 − φ)·f | C36: =(1-$C$22)*$C$20 -> 0.693 | D36: =(1-$C$22)*$C$21 -> 0.297 | E36: =$C$22 -> 0.01 | F36: =SUM(C36:E36) -> 1
A37: > | B37: Étape 4 — bilan de phase solide : masses volumiques et couplage | I37: ρ_v = ε_f·ρ_f + ε_m·ρ_m ; ρ_c = ε_f·ρ_f + Y·ε_m·ρ_m
B38: ρ vierge [kg/m³] | C38: =C36*$C$23+D36*$C$24 -> 1465.2 | I38: attendu 1465.2 (TACOT : 280 — soit 5.2 fois plus dense)
B39: ρ char [kg/m³] | C39: =C36*$C$23+$C$25*D36*$C$24 -> 1287 | I39: attendu 1287.0 (TACOT : 220)
B40: fibres en % de la masse vierge | C40: =C36*$C$23/C38*100 -> 75.675676 | I40: attendu 75.7 % (TACOT : 57.1 %) — le CPh70 est un matériau riche en fibres
B41: gaz de pyrolyse libéré [kg/m³] | C41: =C38-C39 -> 178.2 | I41: attendu 178.2 kg/m³
B42: … soit en % de la masse vierge | C42: =(C38-C39)/C38*100 -> 12.162162 | I42: 12.2 % contre 21.4 % pour le TACOT : deux fois moins de gaz par unité de masse
B43: couplage k = B'g / B'c = (ρ_v − ρ_c)/ρ_c | C43: =(C38-C39)/C39 -> 0.13846154 | I43: attendu 0.1385 — la SEULE grandeur qui distingue le CPh70 du TACOT
A45: §4 — RÉSULTAT : CE QUI ENTRE DANS LE XML
B46: Composition élémentaire (fractions molaires) | C46: C | D46: H | E46: O | F46: Somme
B47: calcul — chaîne complète ci-dessus | C47: =C30 -> 0.20594711 | D47: =D30 -> 0.67898448 | E47: =E30 -> 0.11506842 | F47: =SUM(C47:E47) -> 1
B48: valeur portée dans le XML (cph70_pyro) | C48: 0.206 | D48: 0.679 | E48: 0.115 | F48: =SUM(C48:E48) -> 1
B49: écart relatif |calcul − XML| / XML | C49: =ABS(C47-C48)/C48 -> 0.00025676761 | D49: =ABS(D47-D48)/D48 -> 2.2861076e-05 | E49: =ABS(E47-E48)/E48 -> 0.00059492869
B50: Char (cph70_char) | C50: C | D50: H | E50: O
B51: composition du XML | C51: 1 | D51: — | E51: —
B52: Le fichier cph70-air_25.xml est donc STRICTEMENT identique à tacot-air_25.xml. Il n'est justifié que par la traçabilité — nommer le matériau. La table B'c(T, P, B'g) et h_w(T, P, B'g) sont rigoureusement les mêmes.
A54: §5 — CONTRÔLES ET VALIDATION CROISÉE
A55: > | B55: Contrôle A — écart mesuré entre les tables B' calculées CPh70 et TACOT | I55: sur B'c(T, B'g) aux 4 pressions
B56: écart maximal | C56: 0.000e+00 | I56: vérifié numériquement — cf. tacot_bprime/cph70_vs_tacot.md §1
A57: > | B57: Contrôle B — le B'c RÉELLEMENT atteint diffère, lui : c'est la droite B'g = k·B'c qui change | I57: point fixe : B'c = B'c_table(T, P, B'g = k·B'c)
B58: T [K], 1 atm | C58: TACOT B'c | D58: TACOT B'g | E58: CPh70 B'c | F58: CPh70 B'g | G58: écart sur B'c
B59: 1000 | C59: 0.14221 | D59: 0.0388 | E59: 0.14774 | F59: 0.0205 | G59: =(E59-C59)/C59 -> 0.038886154
B60: 2000 | C60: 0.16684 | D60: 0.0455 | E60: 0.17105 | F60: 0.0237 | G60: =(E60-C60)/C60 -> 0.025233757
B61: 3000 | C61: 0.18962 | D61: 0.0517 | E61: 0.18564 | F61: 0.0257 | G61: =(E61-C61)/C61 -> -0.020989347
B62: 3400 | C62: 0.2409 | D62: 0.0657 | E62: 0.22659 | F62: 0.0314 | G62: =(E62-C62)/C62 -> -0.059402242
B63: 3600 | C63: 0.42054 | D63: 0.1147 | E63: 0.3721 | F63: 0.0515 | G63: =(E63-C63)/C63 -> -0.11518524
B64: Valeurs produites par `python cph70_bprime.py` et `python tacot_bprime/material_response.py`. Sous 3000 K l'écart reste sous ~4 % ; il explose au genou de sublimation, où la courbe B'c(B'g) devient raide. Moins de soufflage pyrolytique ⇒ le char du CPh70 survit à plus haute température.
A66: §6 — SENSIBILITÉ AU RAPPORT FIBRES/RÉSINE
B67: f_fibres (volume solide) | C67: ρ_v [kg/m³] | D67: ρ_c [kg/m³] | E67: k = B'g/B'c | F67: gaz de pyrolyse C | G67: gaz de pyrolyse H | H67: gaz de pyrolyse O
B68: 0.1 | C68: =(1-$C$22)*(B68*$C$23+(1-B68)*$C$24) -> 1227.6 | D68: =(1-$C$22)*(B68*$C$23+$C$25*(1-B68)*$C$24) -> 693 | E68: =(C68-D68)/D68 -> 0.77142857 | F68: =$C$30 -> 0.20594711 | G68: =$D$30 -> 0.67898448 | H68: =$E$30 -> 0.11506842
B69: 0.3 | C69: =(1-$C$22)*(B69*$C$23+(1-B69)*$C$24) -> 1306.8 | D69: =(1-$C$22)*(B69*$C$23+$C$25*(1-B69)*$C$24) -> 891 | E69: =(C69-D69)/D69 -> 0.46666667 | F69: =$C$30 -> 0.20594711 | G69: =$D$30 -> 0.67898448 | H69: =$E$30 -> 0.11506842
B70: 0.5 | C70: =(1-$C$22)*(B70*$C$23+(1-B70)*$C$24) -> 1386 | D70: =(1-$C$22)*(B70*$C$23+$C$25*(1-B70)*$C$24) -> 1089 | E70: =(C70-D70)/D70 -> 0.27272727 | F70: =$C$30 -> 0.20594711 | G70: =$D$30 -> 0.67898448 | H70: =$E$30 -> 0.11506842
B71: 0.7 | C71: =(1-$C$22)*(B71*$C$23+(1-B71)*$C$24) -> 1465.2 | D71: =(1-$C$22)*(B71*$C$23+$C$25*(1-B71)*$C$24) -> 1287 | E71: =(C71-D71)/D71 -> 0.13846154 | F71: =$C$30 -> 0.20594711 | G71: =$D$30 -> 0.67898448 | H71: =$E$30 -> 0.11506842
B72: 0.9 | C72: =(1-$C$22)*(B72*$C$23+(1-B72)*$C$24) -> 1544.4 | D72: =(1-$C$22)*(B72*$C$23+$C$25*(1-B72)*$C$24) -> 1485 | E72: =(C72-D72)/D72 -> 0.04 | F72: =$C$30 -> 0.20594711 | G72: =$D$30 -> 0.67898448 | H72: =$E$30 -> 0.11506842
B73: Les trois dernières colonnes sont CONSTANTES : c'est toute la démonstration de cet onglet. Le rapport fibres/résine déplace k d'un facteur 5 sur la plage balayée, et ne touche pas d'un iota la composition portée dans le XML.
A75: §7 — RÉPONSE MATÉRIAU (n'entre PAS dans le XML)
B76: k du CPh70 | C76: =C43 -> 0.13846154
B77: k du TACOT (rappel) | C77: ='TACOT'!C103 -> 0.27272727
B78: rapport ρ_char CPh70 / ρ_char TACOT | C78: =C39/'TACOT'!C101 -> 5.85 | I78: à B'c égal, la récession ṡ = B'c·ṁe/ρ_c du CPh70 est 5.85 fois plus lente
A80: §8 — BLOC XML
B81: <mixture thermo_db="NASA-9" >
B82: <species>
B83: C H O N CH4 CN CO CO2 C2 C2H C2H2,acetylene C3 C4 C4H2,butadiyne C5
B84: HCN H2 H2O N2 CH2OH CNN CNC CNCOCN C6H6 HNC C(gr)
B85: </species>
B86: <element_compositions default="air">
B87: <composition name="air">N:0.79, O:0.21</composition>
B88: <composition name="cph70_pyro">C:0.206, H:0.679, O:0.115</composition>
B89: <composition name="cph70_char">C:1.0</composition>
B90: </element_compositions>
B91: </mixture>

Sheet ZURAM
A1: ZURAM® 18/50 — carbone/phénolique DLR
A2: Chaîne INVERSE du TACOT : la donnée primaire est une composition élémentaire MASSIQUE mesurée, pas une spéciation moléculaire
A3: Fichier(s) XML : data/mixtures/zuram-air.xml · zuram-pyrogas.xml
A5: §0 — FICHE D'IDENTITÉ
B6: Matériau | C6: ZURAM® 18/50, ablateur carbone/phénolique du DLR | I6: 'ZURAM_official'!A4 du classeur Tacot_Zuram_Calcarb_database_v4.3.1.ods
B7: Renfort | C7: préforme Mersen Calcarb CBCF 18/2000 — « 18 » = 180 kg/m³ nominal | I7: 'Calcarb_official'!D15 ; note de version 4.3.0
B8: Résine | C8: phénolique catalysée à l'hexamine (HMTA) — novolac DÉDUIT, non déclaré | I8: [THo] Aerosp. Sci. Technol. 119 (2021) 107079, § 4.2
B9: « 50 » du nom | C9: teneur en résine, en % masse de la recette — CONFIRMÉ | I9: Pagan et al. 2017, table 1 : les variantes −25 % et −50 % de résine s'appellent 18/43 et 18/33, soit exactement 42.857 % et 33.333 %
B10: Source du gaz | C10: campagne AblaNTIS du VKI, fractions MASSIQUES élémentaires | I10: 'ZURAM_official'!E87:E89
B11: Compositions du XML | C11: BLedge (-bl) · VKIZuramPyroGas (-py) · Char (-char, -char-elem C) | I11: reproduit le cas de référence AblaNTIS carbonPhenolInAir
A13: §1 — HYPOTHÈSES
A14: H1 | B14: La donnée primaire est la composition élémentaire MASSIQUE du gaz, mesurée — il n'y a pas de spéciation moléculaire à sommer. | I14: C'est la différence de fond avec le TACOT : ici le calcul se réduit à une conversion masse → mole. La contrepartie est que la traçabilité s'arrête à trois décimales, la source [4] VKI_ZURAM_characterization n'étant pas publique.
A15: H2 | B15: Conversion effectuée avec les masses molaires DU CLASSEUR (C 12.0107, H 1.00794, O 15.999). | I15: Elles seules reproduisent 'ZURAM_official'!D87:D89 au 4e-16 près. Les masses usuelles donneraient le même résultat à l'arrondi près, mais pas la reproduction exacte.
A16: H3 | B16: Le gaz est déclaré sans azote, bien que la résine en contienne 1.44 % (hexamine). | I16: [THo] mesure un rendement massique constant de 1.5 % de NH3 au-dessus de 500 °C. Comme pour le TACOT, l'azote est traité comme un composé de catalyseur, hors squelette.
A17: H4 | B17: Le char est du carbone pur : C:1.0. | I17: [THo] mesure pourtant C 96.36 / N 0.13 / H 0.08 / O 3.43 % à 800 °C, et le souligne explicitement. L'hypothèse reste licite en ablation (paroi > 2000 K) et c'est elle qui ferme le mieux le bilan (§5, contrôle C).
A18: H5 | B18: Microstructure : densité intrinsèque de matrice INCHANGÉE à la pyrolyse (pure perte de volume). | I18: Anomalie ouverte n° 3 du classeur : « Intrinsic density of charred resin not well evaluated by He pycnometry ». N'affecte que ρ_c et donc k, pas le XML.
A19: H6 | B19: Liste d'espèces = les 20 espèces gazeuses du cas AblaNTIS + C(gr). | I19: Le but est de reproduire EXACTEMENT la table B' de référence Bprime_carbonPhenolInAir_AblaNTIS.txt : on reprend sa liste à l'identique.
A21: §2 — DONNÉES D'ENTRÉE
A22: > | B22: Gaz de pyrolyse — fractions massiques élémentaires mesurées | I22: 'ZURAM_official'!E87:E89
C23: C | D23: H | E23: O | F23: Somme
B24: y_E — fraction massique [-] | C24: 0.457 | D24: 0.162 | E24: 0.381 | F24: =SUM(C24:E24) -> 1
B25: M_E [g/mol] — masses du classeur | C25: =Constantes!$D$7 -> 12.0107 | D25: =Constantes!$D$8 -> 1.00794 | E25: =Constantes!$D$9 -> 15.999
B26: x_E du classeur ('ZURAM_official'!D87:D89) | C26: 0.17094154 | D26: 0.72207125 | E26: 0.10698721
A28: > | B28: Résine vierge et char — campagne [THo] (analyseur élémentaire, fig. 7) | I28: % masse
C29: C | D29: H | E29: N | F29: O | G29: Somme
B30: résine vierge [% masse] | C30: 75.21 | D30: 5.75 | E30: 1.44 | F30: 14.13 | G30: =SUM(C30:F30) -> 96.53
B31: char à 800 °C [% masse] | C31: 96.36 | D31: 0.08 | E31: 0.13 | F31: 3.43 | G31: =SUM(C31:F31) -> 100
B32: La somme de l'analyse de résine vaut 96.5 % (relevé graphique de la fig. 7) : l'étape 1 du contrôle C la renormalise à 100 %. [THo] commente lui-même la discordance sur l'oxygène entre analyseur élémentaire et micropyrolyse, imputée aux composés lourds non détectés.
A34: > | B34: Microstructure — 'ZURAM_official'!D12:F21 | I34: fractions volumiques et densités intrinsèques
B35: Fractions volumiques | C35: pores | D35: fibres | E35: résine | F35: Somme | G35: ρ intrinsèque [g/cm³]
B36: vierge | C36: 0.707299 | D36: 0.129973 | E36: 0.162729 | F36: =SUM(C36:E36) -> 1.000001
B37: char | C37: 0.769174 | D37: 0.129973 | E37: 0.100854 | F37: =SUM(C37:E37) -> 1.000001
B38: densité intrinsèque [g/cm³] | C38: — | D38: 1.5772 | E38: 1.3151
B39: Piège d'unités : l'en-tête du classeur annonce [kg/m³] mais les valeurs sont en g/cm³. Anomalie ouverte n° 2 : 0.129973 × 1577.2 = 205.0 kg/m³ de fibres, soit 14 % de plus que les 180 kg/m³ nominaux de la préforme CBCF 18/2000.
A41: > | B41: Cinétique de pyrolyse — 'ZURAM_official'!B80:B83 | I41: les f_i ont été divisées par la fraction massique de résine pour porter sur la résine seule (B77)
B42: Réaction | C42: f_i [-] | D42: log10 A | E42: E/R [K] | F42: m
B43: réaction 1 | C43: 0.03507 | D43: 5.33 | E43: 8178.5 | F43: 4.3
B44: réaction 2 | C44: 0.027687 | D44: 8.69 | E44: 16068.4 | F44: 3.7
B45: réaction 3 | C45: 0.095981 | D45: 10.6 | E45: 21612.9 | F45: 2.57
B46: réaction 4 | C46: 0.221495 | D46: 11.67 | E46: 26423.8 | F46: 4.63
B47: Σ f_i | C47: =SUM(C43:C46) -> 0.380233
A49: §3 — CALCUL PAS À PAS
A50: > | B50: Étape 1 — conversion masse → mole (c'est TOUT le calcul du XML) | I50: n_E = y_E / M_E ; x_E = n_E / Σ_j n_j
C51: C | D51: H | E51: O | F51: Somme | G51: M_gaz [g/mol] | H51: écart / classeur
B52: n_E = y_E / M_E [mol par gramme de gaz] | C52: =C24/C25 -> 0.038049406 | D52: =D24/D25 -> 0.16072385 | E52: =E24/E25 -> 0.023813988 | F52: =SUM(C52:E52) -> 0.22258725 | G52: =1/F52 -> 4.4926204
B53: x_E = n_E / Σ n_j | C53: =C52/$F$52 -> 0.17094154 | D53: =D52/$F$52 -> 0.72207125 | E53: =E52/$F$52 -> 0.10698721 | F53: =SUM(C53:E53) -> 1 | H53: =MAX(ABS(C53-C26),ABS(D53-D26),ABS(E53-E26)) -> 3.8857806e-16
B54: M_gaz = 1 / Σ(y_E/M_E) = 4.4926 g/mol, contre 4.9990 pour le TACOT : le gaz du ZURAM est plus léger — plus riche en hydrogène (0.722 contre 0.679) et nettement plus pauvre en carbone (0.171 contre 0.206). L'écart avec le classeur (colonne H) vaut ~4e-16.
A56: §4 — RÉSULTAT : CE QUI ENTRE DANS LE XML
B57: Composition élémentaire (fractions molaires) | C57: C | D57: H | E57: O | F57: Somme
B58: calcul — chaîne complète ci-dessus | C58: =C53 -> 0.17094154 | D58: =D53 -> 0.72207125 | E58: =E53 -> 0.10698721 | F58: =SUM(C58:E58) -> 1
B59: valeur portée dans le XML (VKIZuramPyroGas) | C59: 0.171 | D59: 0.722 | E59: 0.107 | F59: =SUM(C59:E59) -> 1
B60: écart relatif |calcul − XML| / XML | C60: =ABS(C58-C59)/C59 -> 0.00034189311 | D60: =ABS(D58-D59)/D59 -> 9.8690338e-05 | E60: =ABS(E58-E59)/E59 -> 0.00011953928
B61: L'écart est celui de l'arrondi à trois décimales. ATTENTION : l'onglet ZURAM_preliminary du même classeur porte une valeur DIFFÉRENTE (C:0.1246, H:0.7506, O:0.1249), issue d'une autre voie — 37 % d'écart sur le carbone. Ce n'est PAS la valeur du XML.
B63: Char (Char) | C63: C | D63: H | E63: O
B64: composition du XML | C64: 1 | D64: — | E64: —
A66: §5 — CONTRÔLES ET VALIDATION CROISÉE
A67: > | B67: Contrôle A — le rendement en char par DEUX voies indépendantes du classeur | I67: (a) volumique : ε_m,char/ε_m,vierge (b) cinétique : 1 − Σ f_i
B68: (a) fractions volumiques de matrice | C68: =E37/E36 -> 0.61976661 | I68: 0.100854 / 0.162729 — licite car la densité intrinsèque de matrice est supposée inchangée (H5)
B69: (b) cinétique de pyrolyse | C69: =1-C47 -> 0.619767 | I69: 1 − Σ f_i sur les 4 réactions
B70: écart entre les deux voies | C70: =ABS(C68-C69) -> 3.9417068e-07 | I70: attendu ~4e-16 — le classeur est cohérent à la dernière décimale
B71: Rendement en char de la résine du ZURAM : 0.6198, contre 0.50 pour le TACOT. Le ZURAM charbonne nettement plus — cohérent avec une résine plus réticulée (motif C7H6O plutôt que C6H6O). Comme pour le TACOT, aucune cellule ne porte ce nombre : il est implicite.
A73: > | B73: Contrôle C — fermeture croisée résine − char → gaz (deux campagnes distinctes) | I73: n_E(gaz) = n_E(résine renormalisée) − n_E(char)
B74: Base 100 g de résine vierge | C74: C | D74: H | E74: O | F74: Somme | G74: écart max / XML
B75: résine renormalisée à 100 % [% masse] | C75: =C30/$G$30*100 -> 77.913602 | D75: =D30/$G$30*100 -> 5.9566974 | E75: =F30/$G$30*100 -> 14.637936
B76: moles d'atomes de la résine | C76: =C75/Constantes!$C$7 -> 6.4868539 | D76: =D75/Constantes!$C$8 -> 5.909422 | E76: =E75/Constantes!$C$9 -> 0.91492821 | F76: =SUM(C76:E76) -> 13.311204
B77: char retranché — carbone pur, Y = 0.6198 | C77: =$C$68*100/Constantes!$C$7 -> 5.1599917 | D77: 0 | E77: 0 | F77: =SUM(C77:E77) -> 5.1599917
B78: gaz obtenu — x_E | C78: =(C76-C77)/($F$76-$F$77) -> 0.16278096 | D78: =(D76-D77)/($F$76-$F$77) -> 0.72497461 | E78: =(E76-E77)/($F$76-$F$77) -> 0.11224443 | F78: =SUM(C78:E78) -> 1 | G78: =MAX(ABS(C78-$C$59)/$C$59,ABS(D78-$D$59)/$D$59,ABS(E78-$E$59)/$E$59) -> 0.049013386
B79: char retranché — char mesuré à 800 °C | C79: =$C$68*100*C31/100/Constantes!$C$7 -> 4.972168 | D79: =$C$68*100*D31/100/Constantes!$C$8 -> 0.049187826 | E79: =$C$68*100*F31/100/Constantes!$C$9 -> 0.13287077 | F79: =SUM(C79:E79) -> 5.1542266
B80: gaz obtenu — x_E | C80: =(C76-C79)/($F$76-$F$79) -> 0.18569205 | D80: =(D76-D79)/($F$76-$F$79) -> 0.71843207 | E80: =(E76-E79)/($F$76-$F$79) -> 0.095875885 | F80: =SUM(C80:E80) -> 1 | G80: =MAX(ABS(C80-$C$59)/$C$59,ABS(D80-$D$59)/$D$59,ABS(E80-$E$59)/$E$59) -> 0.10396369
B81: Accord à 4.9 % avec l'hypothèse de char de carbone pur, contre 10.4 % avec le char réellement mesuré. La composition du gaz vient d'une source VKI, celle de la résine et du char de la campagne [THo] : la fermeture est un VRAI contrôle, pas une tautologie. Le fait que le char pur ferme le mieux suggère que la donnée VKI a elle aussi été établie sous cette hypothèse.
A83: > | B83: Contrôle D — le motif équivalent de la résine | I83: renormalisation hors azote et comparaison aux motifs de l'onglet Constantes
B84: Composition hors azote [% masse] | C84: C | D84: H | E84: O | F84: écart max au motif
B85: ZURAM mesuré, renormalisé hors N | C85: =C30/(C30+D30+F30)*100 -> 79.09349 | D85: =D30/(C30+D30+F30)*100 -> 6.0469029 | E85: =F30/(C30+D30+F30)*100 -> 14.859607
B86: phénol C6H6O | C86: =Constantes!$F$25 -> 76.573906 | D86: =Constantes!$G$25 -> 6.4263173 | E86: =Constantes!$H$25 -> 16.999777 | F86: =MAX(ABS(C86-$C$85),ABS(D86-$D$85),ABS(E86-$E$85)) -> 2.5195845
B87: novolac linéaire C7H6O | C87: =Constantes!$F$26 -> 79.225246 | D87: =Constantes!$G$26 -> 5.6989936 | E87: =Constantes!$H$26 -> 15.07576 | F87: =MAX(ABS(C87-$C$85),ABS(D87-$D$85),ABS(E87-$E$85)) -> 0.3479093
B88: résol saturé C7.5H6O | C88: =Constantes!$F$27 -> 80.337913 | D88: =Constantes!$G$27 -> 5.3937635 | E88: =Constantes!$H$27 -> 14.268324 | F88: =MAX(ABS(C88-$C$85),ABS(D88-$D$85),ABS(E88-$E$85)) -> 1.2444225
B89: Le ZURAM tombe à 0.35 point du novolac linéaire C7H6O — contre 0.85 point du phénol C6H6O pour le TACOT. Les deux résines emploient très vraisemblablement la même chimie ; c'est la quantité de composés piégés (eau, HMTA) qui distingue les deux analyses. Combiné à l'hexamine, c'est ce qui fait déduire « novolac ».
A91: §6 — SENSIBILITÉ
B92: Le gaz du XML ne dépend d'AUCUNE des hypothèses de rendement ou de motif : il est mesuré directement (§3, une seule étape). Les sensibilités portent donc sur les CONTRÔLES, pas sur le résultat — c'est l'inverse du SC-1008 et du liège, où le rendement en char entre dans la chaîne de calcul du XML.
B93: Rendement en char testé | C93: C | D93: H | E93: O | F93: écart max / XML
B94: 0.55 | C94: =($C$76-B94*100/Constantes!$C$7)/($F$76-B94*100/Constantes!$C$7) -> 0.21847265 | D94: =$D$76/($F$76-B94*100/Constantes!$C$7) -> 0.6767494 | E94: =$E$76/($F$76-B94*100/Constantes!$C$7) -> 0.10477795 | F94: =MAX(ABS(C94-$C$59)/$C$59,ABS(D94-$D$59)/$D$59,ABS(E94-$E$59)/$E$59) -> 0.27761783
B95: 0.6 | C95: =($C$76-B95*100/Constantes!$C$7)/($F$76-B95*100/Constantes!$C$7) -> 0.17934967 | D95: =$D$76/($F$76-B95*100/Constantes!$C$7) -> 0.71062723 | E95: =$E$76/($F$76-B95*100/Constantes!$C$7) -> 0.11002309 | F95: =MAX(ABS(C95-$C$59)/$C$59,ABS(D95-$D$59)/$D$59,ABS(E95-$E$59)/$E$59) -> 0.048828506
B96: 0.619766 | C96: =($C$76-B96*100/Constantes!$C$7)/($F$76-B96*100/Constantes!$C$7) -> 0.16278148 | D96: =$D$76/($F$76-B96*100/Constantes!$C$7) -> 0.72497416 | E96: =$E$76/($F$76-B96*100/Constantes!$C$7) -> 0.11224436 | F96: =MAX(ABS(C96-$C$59)/$C$59,ABS(D96-$D$59)/$D$59,ABS(E96-$E$59)/$E$59) -> 0.049012737
B97: 0.65 | C97: =($C$76-B97*100/Constantes!$C$7)/($F$76-B97*100/Constantes!$C$7) -> 0.13610332 | D97: =$D$76/($F$76-B97*100/Constantes!$C$7) -> 0.74807562 | E97: =$E$76/($F$76-B97*100/Constantes!$C$7) -> 0.11582105 | F97: =MAX(ABS(C97-$C$59)/$C$59,ABS(D97-$D$59)/$D$59,ABS(E97-$E$59)/$E$59) -> 0.20407414
B98: Le minimum d'écart tombe près de la valeur du classeur — le rendement en char déduit de la microstructure est compatible avec la composition du gaz mesurée indépendamment.
A100: §7 — RÉPONSE MATÉRIAU (n'entre PAS dans le XML)
B101: ρ vierge [kg/m³] | C101: =(D36*D38+E36*E38)*1000 -> 418.99832 | I101: 'ZURAM_official'!D17 — attendu 419.0
B102: ρ char [kg/m³] | C102: =(D37*D38+E37*E38)*1000 -> 337.62651 | I102: 'ZURAM_official'!E17 — attendu 337.6
B103: fibres seules [kg/m³] | C103: =D36*D38*1000 -> 204.99342 | I103: 205.0 au lieu des 180 nominaux — anomalie ouverte n° 2 du classeur
B104: résine en % de la masse vierge | C104: =E36*E38*1000/C101*100 -> 51.075361 | I104: 51.07 % (TACOT : 42.9 %) pour 16.3 % du volume
B105: gaz libéré [kg/m³] | C105: =C101-C102 -> 81.371813 | I105: 81.4 kg/m³, soit 19.4 % de la masse vierge (TACOT : 21.4 %)
B106: couplage k = B'g / B'c | C106: =(C101-C102)/C102 -> 0.24101132 | I106: attendu 0.2410 (TACOT : 0.2727)
A108: §8 — BLOC XML
B109: <mixture thermo_db="NASA-9">
B110: <species>
B111: C(gr) C H O N CH CH4 CO CO2 CN C2H C2H2,acetylene C3 C3H C4
B112: C4H2,butadiyne C5 HCN H2 H2O N2
B113: </species>
B114: <element_compositions default="BLedge">
B115: <composition name="BLedge"> O:0.21, N:0.79 </composition>
...

Sheet SC-1008
A1: SC-1008 — résol phénol-formaldéhyde (matrice du PICA)
A2: Gaz obtenu par FERMETURE ÉLÉMENTAIRE sur un motif chimique idéalisé, validé contre une mesure indépendante
A3: Fichier(s) XML : data/mixtures/sc1008-air.xml · sc1008-pyrogas.xml
A5: §0 — FICHE D'IDENTITÉ
B6: Résine | C6: Durite™ SC-1008, Hexion / Bakelite Synthetics (ex-Borden) | I6: [Wo] J. Anal. Appl. Pyrolysis 122 (2016) 258-267, § 2.2
B7: Type | C7: RÉSOL phénol-formaldéhyde, monocomposant, réticulant par chauffage seul | I7: excès de formaldéhyde, catalyse basique : porte déjà ses méthylols, durcit sans durcisseur
B8: Emploi | C8: matrice du PICA, sur préforme carbone FiberForm | I8: densité PICA 0.274 g/cm³ ± 10 %, porosité 0.8 ± 10 %
B9: Livraison | C9: 20-25 % isopropanol · 11-18 % phénol libre · 0.6-2 % formaldéhyde libre | I9: [Wo] § 2.2 — le phénol libre part en région 1 sans venir du réseau
B10: Sources | C10: [TS] Trick & Saliba, Carbon 33 (1995) 1509-1515 · [Wo] Wong et al. 2016 | I10: sc1008_bprime/resine_sc1008.md
B11: Compositions du XML | C11: air (-bl) · sc1008_pyro (-py) · sc1008_char (-char, -char-elem C)
A13: §1 — HYPOTHÈSES
A14: H1 | B14: Une résine résol cuite = un cycle phénolique + ses ponts méthylène : motif C(6+b)H6O. | I14: Le nombre de ponts b n'est pas libre : le phénol a 3 sites réactifs (2 ortho + 1 para) et un pont est partagé entre 2 cycles, d'où b = 1.5 à réseau saturé.
A15: H2 | B15: PAS D'AZOTE dans le gaz — et cette fois ce n'est pas une approximation. | I15: Un résol réticule sans durcisseur : il n'y a pas d'hexaméthylènetétramine dans la formulation. Le gaz est NATIVEMENT C/H/O. L'argument que le TACOT (2.35 % N) et le ZURAM (1.4 %) doivent construire est ici sans objet.
A16: H3 | B16: Le char est du carbone pur ⇒ H et O traversent la pyrolyse sans être touchés. | I16: Conséquence remarquable : H/O(gaz) = H/O(résine) INDÉPENDAMMENT du rendement en char. C'est l'invariant du §5, un test qui ne dépend d'aucune hypothèse fragile.
A17: H4 | B17: Rendement en char Y = 0.55. | I17: Ce n'est PAS la moyenne des trois sources (0.545 / 0.55-0.60 / 0.62) : le milieu arithmétique 0.575 s'écarte de [TS] de 8.9 %. 0.55 est la seule valeur qui tombe dans la fourchette ATG ET reproduise la composition de [TS] à 1.5 %.
A18: H5 | B18: La borne haute Y = 0.62 de [Wo] est PROPRE AU PICA et ne vaut pas pour la résine seule. | I18: La préforme carbone capte des radicaux pendant la pyrolyse et relève le rendement — [Wo] l'observe directement : H2 divisé par ~5 par rapport à la résole nue.
A19: H6 | B19: Liste d'espèces = les 25 de la table B' de référence + phénol + C(gr). | I19: Le phénol et le crésol sont les produits dominants EN MASSE de la pyrolyse d'un résol ([TS] région 1 ; [Wo] table 1) : les omettre appauvrirait l'équilibre pariétal.
A21: §2 — DONNÉES D'ENTRÉE
B22: nombre de ponts méthylène par cycle, b | C22: 1.5 | I22: 3 sites réactifs / 2 cycles par pont — cf. H1
B23: rendement en char de la résine, Y | C23: 0.55 | I23: recoupement [TS] (0.545) et ATG SC-1008 nue (0.55-0.60) — cf. H4
B24: composition mesurée de [TS] — C | C24: 0.2564 | I24: reconstruite au §5 depuis les tables 2 et 4 de Trick & Saliba (LMS = 50/50 phénol/crésol)
B25: H | C25: 0.6388
B26: O | C26: 0.1048
A28: §3 — CALCUL PAS À PAS
A29: > | B29: Étape 1 — construire le motif de la résine cuite | I29: phénol C6H6O + b·CH2O − b·H2O
B30: Brique | C30: coefficient | D30: ν_C | E30: ν_H | F30: ν_O
B31: phénol C6H6O | C31: 1 | D31: 6 | E31: 6 | F31: 1
B32: + formaldéhyde CH2O | C32: =$C$22 -> 1.5 | D32: 1 | E32: 2 | F32: 1
B33: − eau de condensation H2O | C33: =-$C$22 -> -1.5 | D33: 0 | E33: 2 | F33: 1
B34: MOTIF CUIT — ν_E = Σ coeff · ν | D34: =SUMPRODUCT($C$31:$C$33,D31:D33) -> 7.5 | E34: =SUMPRODUCT($C$31:$C$33,E31:E33) -> 6 | F34: =SUMPRODUCT($C$31:$C$33,F31:F33) -> 1
B35: Avec b = 1.5 : C7.5H6O. Noter que H et O sont RIGOUREUSEMENT insensibles à b (+2b des formaldéhydes, −2b des eaux) : seul le carbone bouge. C'est la raison profonde de l'invariant H/O du §5.
A36: > | B36: Étape 2 — masse molaire et composition massique du motif | I36: M = ν_C·M_C + ν_H·M_H + ν_O·M_O ; w_E = ν_E·M_E / M
C37: C | D37: H | E37: O | F37: M [g/mol]
B38: ν_E · M_E [g/mol] | C38: =D34*Constantes!$C$7 -> 90.0825 | D38: =E34*Constantes!$C$8 -> 6.048 | E38: =F34*Constantes!$C$9 -> 15.999 | F38: =SUM(C38:E38) -> 112.1295
B39: w_E [% masse] | C39: =C38/$F$38*100 -> 80.337913 | D39: =D38/$F$38*100 -> 5.3937635 | E39: =E38/$F$38*100 -> 14.268324 | F39: =SUM(C39:E39) -> 100
B40: Attendu : M = 112.13 g/mol, soit C 80.3 % / H 5.4 % / O 14.3 % en masse. L'écart résol (b = 1.5) / novolac (b = 1) ne vaut que 1.1 point sur C — plus PETIT que la dispersion entre deux novolacs réellement mesurés (TACOT 77.4 vs ZURAM 79.1). L'analyse C/H/O ne permet donc PAS d'identifier le type de résine ; seul l'azote le fait.
A41: > | B41: Étape 3 — fermeture élémentaire sur 100 g de résine : gaz = résine − char | I41: n_E(gaz) = n_E(résine) − n_E(char) ; n_C(char) = Y·100 / M_C
B42: Base 100 g de résine vierge | C42: C | D42: H | E42: O | F42: Somme | G42: masse [g]
B43: résine — moles d'atomes | C43: =100/$F$38*D34 -> 6.6886948 | D43: =100/$F$38*E34 -> 5.3509558 | E43: =100/$F$38*F34 -> 0.89182597 | F43: =SUM(C43:E43) -> 12.931477 | G43: =C43*Constantes!$C$7+D43*Constantes!$C$8+E43*Constantes!$C$9 -> 100
B44: char — carbone pur, Y = 0.55 | C44: =$C$23*100/Constantes!$C$7 -> 4.5791358 | D44: 0 | E44: 0 | F44: =SUM(C44:E44) -> 4.5791358 | G44: =$C$23*100 -> 55
B45: gaz — moles d'atomes | C45: =C43-C44 -> 2.109559 | D45: =D43-D44 -> 5.3509558 | E45: =E43-E44 -> 0.89182597 | F45: =SUM(C45:E45) -> 8.3523408 | G45: =F43-F44 -> 8.3523408
A46: > | B46: Étape 4 — normaliser en fractions molaires, et convertir en fractions massiques | I46: x_E = n_E / Σ n_j ; y_E = x_E·M_E / Σ x_j·M_j
C47: C | D47: H | E47: O | F47: Somme | G47: M_gaz [g/mol] | H47: H/O
B48: x_E (fraction molaire élémentaire) | C48: =C45/$F$45 -> 0.25257099 | D48: =D45/$F$45 -> 0.64065344 | E48: =E45/$F$45 -> 0.10677557 | F48: =SUM(C48:E48) -> 1 | G48: =C48*Constantes!$C$7+D48*Constantes!$C$8+E48*Constantes!$C$9 -> 5.3877112 | H48: =D48/E48 -> 6
B49: y_E (fraction massique élémentaire) | C49: =C48*Constantes!$C$7/$G$48 -> 0.56306473 | D49: =D48*Constantes!$C$8/$G$48 -> 0.11986141 | E49: =E48*Constantes!$C$9/$G$48 -> 0.31707386 | F49: =SUM(C49:E49) -> 1
B50: La ligne massique est l'équivalent strict à déclarer si l'on écrit <composition name="sc1008_pyro" type="mass">C:0.563, H:0.120, O:0.317</composition>. Sans l'attribut type="mass", le parseur suppose du molaire — et le mélange serait faux.
A52: §4 — RÉSULTAT : CE QUI ENTRE DANS LE XML
B53: Composition élémentaire (fractions molaires) | C53: C | D53: H | E53: O | F53: Somme
B54: calcul — chaîne complète ci-dessus | C54: =C48 -> 0.25257099 | D54: =D48 -> 0.64065344 | E54: =E48 -> 0.10677557 | F54: =SUM(C54:E54) -> 1
B55: valeur portée dans le XML (sc1008_pyro) | C55: 0.2526 | D55: 0.6407 | E55: 0.1068 | F55: =SUM(C55:E55) -> 1.0001
B56: écart relatif |calcul − XML| / XML | C56: =ABS(C54-C55)/C55 -> 0.00011484491 | D56: =ABS(D54-D55)/D55 -> 7.2675212e-05 | E56: =ABS(E54-E55)/E55 -> 0.0002287188
B57: Char (sc1008_char) | C57: C | D57: H | E57: O
B58: composition du XML | C58: 1 | D58: — | E58: —
A60: §5 — CONTRÔLES ET VALIDATION CROISÉE
A61: > | B61: Contrôle A — l'invariant H/O : il ne dépend PAS du rendement en char | I61: H/O(gaz) = H/O(résine), car un char de carbone pur ne prélève que du C
B62: Y testé | C62: C | D62: H | E62: O | F62: H/O | G62: verdict
B63: 0.3 | C63: =($C$43-B63*100/Constantes!$C$7)/($F$43-B63*100/Constantes!$C$7) -> 0.40167513 | D63: =$D$43/($F$43-B63*100/Constantes!$C$7) -> 0.51284989 | E63: =$E$43/($F$43-B63*100/Constantes!$C$7) -> 0.085474982 | F63: =D63/E63 -> 6 | G63: constant
B64: 0.5 | C64: =($C$43-B64*100/Constantes!$C$7)/($F$43-B64*100/Constantes!$C$7) -> 0.28805472 | D64: =$D$43/($F$43-B64*100/Constantes!$C$7) -> 0.61023881 | E64: =$E$43/($F$43-B64*100/Constantes!$C$7) -> 0.10170647 | F64: =D64/E64 -> 6 | G64: constant
B65: 0.55 | C65: =($C$43-B65*100/Constantes!$C$7)/($F$43-B65*100/Constantes!$C$7) -> 0.25257099 | D65: =$D$43/($F$43-B65*100/Constantes!$C$7) -> 0.64065344 | E65: =$E$43/($F$43-B65*100/Constantes!$C$7) -> 0.10677557 | F65: =D65/E65 -> 6 | G65: constant
B66: 0.7 | C66: =($C$43-B66*100/Constantes!$C$7)/($F$43-B66*100/Constantes!$C$7) -> 0.1211664 | D66: =$D$43/($F$43-B66*100/Constantes!$C$7) -> 0.75328594 | E66: =$E$43/($F$43-B66*100/Constantes!$C$7) -> 0.12554766 | F66: =D66/E66 -> 6 | G66: constant
B67: Bornes : aucun motif phénolique concevable ne descend sous H/O = 3.6 (résol prépolymère non cuit C7.5H9O2.5), et ajouter de l'eau ne sauve rien — C7.5H6O·(H2O)w donne H/O = (6+2w)/(1+w), qui tend vers 2.0 PAR LE HAUT. C'est ce test qui a fait supprimer du dépôt le jeu PICA hérité de Goldstein, à H/O = 1.93 : il n'était reproductible par AUCUNE résine phénolique, à AUCUN degré de cuisson, avec AUCUNE quantité d'eau ajoutée. Valeurs du dépôt : tacot_pyro 5.90 · cph70_pyro 5.90 · VKIZuramPyroGas 6.75 · sc1008_pyro 6.00 · [TS] mesuré 6.10 · cork_pyro 4.89 (hors test : le liège n'est pas un phénolique).
A69: > | B69: Contrôle B — reconstruction INDÉPENDANTE de la mesure de [TS] : ni motif, ni rendement en char n'y entrent | I69: les tables 2 et 4 de [TS] se recoupent : f_ij·N_i / (f_kj·N_k) = d_ij / d_kj
B70: Espèce | C70: table 2 — R1 [%] | D70: table 2 — R2 [%] | E70: table 2 — R3 [%] | F70: table 4 — R1 [%] | G70: table 4 — R2 [%] | H70: table 4 — R3 [%]
B71: H2 | C71: 0 | D71: 59.4 | E71: 85.7 | F71: 0 | G71: 57.1 | H71: 42.9
B72: H2O | C72: 49.8 | D72: 12.7 | E72: 4.7 | F72: 66.3 | G72: 28.2 | H72: 5.5
B73: LMS (phénol + crésol) | C73: 50.1 | D73: 0 | E73: 0 | F73: 100 | G73: 0 | H73: 0
B74: CO | C74: 0 | D74: 12.7 | E74: 9.5 | F74: 0 | G74: 71.9 | H74: 28.1
B75: CH4 | C75: 0 | D75: 14.9 | E75: 0 | F75: 0 | G75: 100 | H75: 0
B76: CO2 | C76: 0.1 | D76: 0.2 | E76: 0.1 | F76: 20.5 | G76: 66.8 | H76: 12.7
B77: C2H6 | C77: 0 | D77: 0.1 | E77: 0 | F77: 0 | G77: 100 | H77: 0
B78: Table 2 = composition molaire DANS chaque région réactionnelle ; table 4 = distribution de chaque espèce SUR les régions (% du total). Régions : R1 300-550 °C, R2 400-800 °C, R3 560-900 °C. Aucune des deux ne donne la composition globale — mais elles se recoupent.
B79: Estimation de N2/N3 par espèce commune | C79: valeur | D79: retenue ?
B80: via H2O | C80: =(G72/H72)*(E72/D72) -> 1.8974946 | D80: oui
B81: via H2 | C81: =(G71/H71)*(E71/D71) -> 1.9203182 | D81: oui
B82: via CO | C82: =(G74/H74)*(E74/D74) -> 1.9140023 | D82: oui
B83: via CO2 | C83: =(G76/H76)*(E76/D76) -> 2.6299213 | D83: écartée : CO2 pèse 0.1-0.2 % dans la table 2, l'arrondi y domine le signal
B84: moyenne des trois retenues | C84: =AVERAGE(C80:C82) -> 1.910605 | D84: accord à 1.2 %
B85: N1/N2 via H2O (seule espèce commune à R1 et R2) | C85: =(F72/G72)*(D72/C72) -> 0.59956849
B86: Tailles relatives des régions (N3 = 1) | C86: N1 | D86: N2 | E86: N3
B87: N_i | C87: =C85*C84 -> 1.1455386 | D87: =C84 -> 1.910605 | E87: 1
B88: Composition moléculaire globale reconstruite | C88: n_j = Σ_i N_i·f_ij | D88: x_j | E88: ν_C | F88: ν_H | G88: ν_O
B89: H2 | C89: =SUMPRODUCT($C$87:$E$87,C71:E71) -> 199.18994 | D89: =C89/$C$96 -> 0.49108207 | E89: 0 | F89: 2 | G89: 0
B90: H2O | C90: =SUMPRODUCT($C$87:$E$87,C72:E72) -> 86.012505 | D90: =C90/$C$96 -> 0.21205488 | E90: 0 | F90: 2 | G90: 1
B91: LMS (phénol + crésol) | C91: =SUMPRODUCT($C$87:$E$87,C73:E73) -> 57.391482 | D91: =C91/$C$96 -> 0.14149273 | E91: 6.5 | F91: 7 | G91: 1
B92: CO | C92: =SUMPRODUCT($C$87:$E$87,C74:E74) -> 33.764684 | D92: =C92/$C$96 -> 0.083243315 | E92: 1 | F92: 0 | G92: 1
B93: CH4 | C93: =SUMPRODUCT($C$87:$E$87,C75:E75) -> 28.468015 | D93: =C93/$C$96 -> 0.070184929 | E93: 1 | F93: 4 | G93: 0
B94: CO2 | C94: =SUMPRODUCT($C$87:$E$87,C76:E76) -> 0.59667486 | D94: =C94/$C$96 -> 0.0014710398 | E94: 1 | F94: 0 | G94: 2
B95: C2H6 | C95: =SUMPRODUCT($C$87:$E$87,C77:E77) -> 0.1910605 | D95: =C95/$C$96 -> 0.00047103979 | E95: 2 | F95: 6 | G95: 0
B96: SOMME | C96: =SUM(C89:C95) -> 405.61436 | D96: =SUM(D89:D95) -> 1
B97: ν du LMS : phénol C6H6O et crésol C7H8O ne sont pas résolus par [TS]. L'hypothèse 50/50 donne C6.5H7O — c'est LA seule hypothèse vraiment libre de ce contrôle. Sensibilité : 100 % phénol → H/O 5.77 · 50/50 → 6.10 · 100 % crésol → 6.42. L'invariant H/O ≈ 6 tient sur toute la plage.
B98: [TS] reconstruit — composition élémentaire | C98: C | D98: H | E98: O | F98: Somme | G98: H/O | H98: écart / XML
B99: n_E = Σ_j ν_E,j · x_j | C99: =SUMPRODUCT($D$89:$D$95,E89:E95) -> 1.0755441 | D99: =SUMPRODUCT($D$89:$D$95,F89:F95) -> 2.6802889 | E99: =SUMPRODUCT($D$89:$D$95,G89:G95) -> 0.439733 | F99: =SUM(C99:E99) -> 4.195566
B100: x_E | C100: =C99/$F$99 -> 0.25635256 | D100: =D99/$F$99 -> 0.63883846 | E100: =E99/$F$99 -> 0.10480898 | F100: =SUM(C100:E100) -> 1 | G100: =D100/E100 -> 6.0952645 | H100: =MAX(ABS(C100-$C$55)/$C$55,ABS(D100-$D$55)/$D$55,ABS(E100-$E$55)/$E$55) -> 0.018642498
B101: DEUX CHAÎNES DE RAISONNEMENT ENTIÈREMENT DISJOINTES — l'une partant d'une mesure de gaz déconvoluée en régions réactionnelles, l'autre d'un motif chimique idéalisé et d'un bilan de masse — convergent à 2 % : 1.5 % sur C, 0.3 % sur H, 1.9 % sur O. C'est la validation centrale de cette mise en données.
A103: > | B103: Contrôle C — pourquoi [Wo] n'est PAS utilisé comme composition élémentaire | I103: pourtant la mesure la plus directe : SC-1008 réel, 16 espèces, 20 paliers
B104: Traitement de la donnée [Wo] | C104: C | D104: H | E104: O | F104: H/O | G104: masse [mg/100 mg]
B105: brut, table 1 intégrée | C105: 0.12 | D105: 0.642 | E105: 0.238 | F105: =D105/E105 -> 2.697479 | G105: 24.5
B106: A : − eau à T ≤ 664 K | C106: 0.138 | D106: 0.639 | E106: 0.223 | F106: =D106/E106 -> 2.8654709 | G106: 21.2
B107: B : + eau > 850 K (attribution de [Wo]) | C107: 0.222 | D107: 0.622 | E107: 0.156 | F107: =D107/E107 -> 3.9871795 | G107: 13
B108: C : calage sur la balance | C108: 0.154 | D108: 0.635 | E108: 0.211 | F108: =D108/E108 -> 3.0094787 | G108: 19
...

Sheet MX-4926
A1: MX-4926 — carbone/phénolique chargé noir de carbone
A2: Matrice SC-1008 : le gaz est HÉRITÉ · démontre que le taux de charge n'entre pas dans le XML, et que la fermeture Σw = 1 tronque une des plages annoncées
A3: Fichier(s) XML : data/mixtures/mx4926-air.xml
A5: §0 — FICHE D'IDENTITÉ
B6: Matériau | C6: MX-4926 — carbone/phénolique chargé | I6: matériau de tuyère de moteur à propergol solide
B7: Renfort | C7: fibres de carbone ex-rayon (ex-cellulose), tissu satin de 5 ou de 8 | I7: le satin accommode les formes complexes et tient la stabilité dimensionnelle
B8: Matrice | C8: résol phénol-formaldéhyde SC-1008 — IDENTIQUE au PICA | I8: cf. onglet SC-1008 §0 ; liant à haut rendement en char
B9: Charge | C9: noir de carbone | I9: optimise l'isolation thermique et la formation du char
B10: Source du gaz | C10: route C, HÉRITÉE du SC-1008 (résine inchangée) | I10: mx4926_bprime/composition_mx4926.md §2.1
B11: Compositions du XML | C11: air (-bl) · mx4926_pyro (-py) · mx4926_char (-char, -char-elem C) | I11: mx4926_bprime/README.md
A13: §1 — HYPOTHÈSES
A14: H1 | B14: La matrice est RIGOUREUSEMENT le SC-1008 de l'onglet précédent : même motif C7.5H6O, même rendement en char. | I14: C'est la seule chose dont dépend la composition du gaz. Tout le §3 de l'onglet SC-1008 s'applique tel quel et n'est PAS refait ici.
A15: H2 | B15: Le renfort ex-rayon ne dégaze pas : une fibre de carbone est déjà le produit d'une pyrolyse. | I15: Perte de masse nulle jusqu'au domaine de sublimation. Contre-exemple : le liège, qui pyrolyse — son onglet doit alors fermer sur DEUX constituants.
A16: H3 | B16: Le noir de carbone est inerte et ne dégaze pas non plus. | I16: Carbone quasi pur (97-99 % C). Du point de vue du bilan de surface il se comporte exactement comme des fibres.
A17: H4 | B17: Les trois constituants carbonisent vers le carbone pur ⇒ char C:1.0 quelles que soient les proportions. | I17: La pondération n_E(char) = Σ_i (m_char,i/M_i)·ν_E,i se réduit à C:1.0 dès que tous les constituants donnent le même élément.
A18: H5 | B18: Aucune grandeur volumique n'entre dans le bilan de surface. | I18: Le bilan est écrit sur des fractions massiques élémentaires, donc normalisées : ni ρ, ni porosité (Constantes §4).
A19: H6 | B19: Les trois plages de composition annoncées doivent se refermer à 100 %. | I19: Elles sont données indépendamment les unes des autres, mais ne peuvent pas l'être : c'est l'objet de l'étape 1 du §3.
A21: §2 — DONNÉES D'ENTRÉE
B22: Fractions MASSIQUES annoncées | C22: borne basse | D22: borne haute
B23: renfort — fibres de carbone ex-rayon | C23: 0.41 | D23: 0.56
B24: matrice — résol SC-1008 | C24: 0.31 | D24: 0.37
B25: charge — noir de carbone | C25: 0.11 | D25: 0.16
B26: SOMME | C26: =SUM(C23:C25) -> 0.83 | D26: =SUM(D23:D25) -> 1.09
B27: Ces deux sommes sont le point de départ de tout l'onglet : 0.830 et 1.090. Elles encadrent 1 sans le valoir — les trois plages ne sont donc pas indépendantes.
B28: rendement en char de la RÉSINE, Y | C28: ='SC-1008'!C23 -> 0.55 | I28: lien vers l'onglet SC-1008 §2 : 0.55, recoupement [TS] et ATG
B29: ρ intrinsèque fibres [kg/m³] | C29: 1600 | I29: fibres ex-cellulose — Description!A11 du classeur TACOT 3.0 ; le rayon EST une cellulose régénérée
B30: ρ intrinsèque résol cuit [kg/m³] | C30: 1250 | I30: valeur usuelle d'un phénolique cuit (1200-1300)
B31: ρ intrinsèque noir de carbone [kg/m³] | C31: 1800 | I31: valeur usuelle (1800-2100)
B32: densité publiée du MX-4926 [kg/m³] | C32: 1450 | I32: ≈ 1.45 g/cm³ — sert au contrôle C du §5, pas au calcul
A34: §3 — CALCUL PAS À PAS
A35: > | B35: Étape 1 — FERMETURE : les plages effectives ne sont pas les plages annoncées | I35: w_i,min_eff = MAX(w_i,min ; 1 − Σ_{j≠i} w_j,max) et symétriquement
B36: Plages EFFECTIVES après fermeture | C36: min | D36: max | E36: annoncé min | F36: annoncé max | G36: largeur perdue
B37: renfort | C37: =MAX(C23,1-D24-D25) -> 0.47 | D37: =MIN(D23,1-C24-C25) -> 0.56 | E37: =C23 -> 0.41 | F37: =D23 -> 0.56 | G37: =(D23-C23)-(D37-C37) -> 0.06
B38: matrice | C38: =MAX(C24,1-D23-D25) -> 0.31 | D38: =MIN(D24,1-C23-C25) -> 0.37 | E38: =C24 -> 0.31 | F38: =D24 -> 0.37 | G38: =(D24-C24)-(D38-C38) -> 0
B39: charge | C39: =MAX(C25,1-D23-D24) -> 0.11 | D39: =MIN(D25,1-C23-C24) -> 0.16 | E39: =C25 -> 0.11 | F39: =D25 -> 0.16 | G39: =(D25-C25)-(D39-C39) -> 0
B40: Une seule ligne a une largeur perdue non nulle : le RENFORT, dont la borne basse passe de 41 % à 47 %. Pour descendre à 41 % de fibres il faudrait 59 % de résine + charge, alors que le maximum admissible est 37 + 16 = 53 %. Les 41 % annoncés ne sont atteignables avec AUCUN couple (résine, charge) admissible. Les plages de la matrice et de la charge survivent intactes — et c'est la matrice qui pilote toute la suite (étape 4).
A41: > | B41: Étape 2 — composition retenue : le centroïde du domaine admissible | I41: centroïde d'AIRE du polygone (5 sommets), pas une moyenne de grille
B42: Composition retenue (fractions massiques) | C42: renfort | D42: matrice | E42: charge | F42: Somme
B43: centroïde exact du polygone admissible | C43: 0.52202381 | D43: 0.34166667 | E43: =1-C43-D43 -> 0.13630952 | F43: =SUM(C43:E43) -> 1
B44: Les deux valeurs bleues sont produites par mx4926_bprime/composition_mx4926_verification.py §2 (clipping de Sutherland-Hodgman, puis formule du centroïde d'aire) : un polygone à 5 sommets ne se moyenne pas à la main. La CHARGE n'est pas saisie : elle est fermée par différence, de sorte que Σw = 1 exactement quel que soit l'arrondi des deux autres — saisir les trois arrondies à 1e-6 briserait la fermeture de 1e-6. Le contrôle D du §5 vérifie que le point tombe bien dans les plages effectives ci-dessus.
A45: > | B45: Étape 3 — gaz de pyrolyse : HÉRITÉ, pas recalculé | I45: Y_g(MX-4926) = Y_g(SC-1008), par H1 + H2 + H3
B46: Gaz de pyrolyse | C46: C | D46: H | E46: O | F46: Somme | G46: H/O
B47: reprise de l'onglet SC-1008 (fermeture élémentaire, route C) | C47: ='SC-1008'!C48 -> 0.25257099 | D47: ='SC-1008'!D48 -> 0.64065344 | E47: ='SC-1008'!E48 -> 0.10677557 | F47: =SUM(C47:E47) -> 1 | G47: =D47/E47 -> 6
B48: Le gaz est produit par la RÉSINE SEULE. Le renfort ex-rayon est déjà carbonisé (H2) et le noir de carbone est inerte (H3) : aucun des deux ne dégaze. La matrice étant le SC-1008, la composition élémentaire du gaz est celle du SC-1008 — toute sa traçabilité (motif C7.5H6O, fermeture à Y = 0.55, confrontation à [TS]) est celle de l'onglet précédent. Le taux de charge et le rapport fibres/résine changent la QUANTITÉ de gaz produite, donc B'g, qui est un paramètre d'ENTRÉE de la table.
A49: > | B49: Étape 4 — char : pondération générale des TROIS constituants | I49: n_E(char) = Σ_i (m_char,i / M_i) · ν_E,i
B50: Fibres ex-rayon : carbone pur. Noir de carbone : carbone pur. Résol carbonisé : carbone pur. La somme pondérée de trois compositions identiques est cette composition, quelles que soient les masses : le char vaut C:1.0 pour TOUT jeu de proportions. C'est ce qui rendrait le calcul faux avec des fibres de silice, un char retenant H/O, ou une charge non carbonée.
A51: > | B51: Étape 5 — rendement en char du COMPOSITE : la fermeture le simplifie | I51: Y_comp = w_f + w_c + Y·w_r = 1 − (1 − Y)·w_r
B52: Rendement en char du composite | C52: forme longue | D52: forme courte | E52: écart
B53: Y_comp | C53: =C43+E43+$C$28*D43 -> 0.84625 | D53: =1-(1-$C$28)*D43 -> 0.84625 | E53: =C53-D53 -> 0
B54: LE POINT DE CET ONGLET. Le renfort et la charge ne perdent pas de masse (H2, H3) ; en utilisant w_f + w_c = 1 − w_r, les deux disparaissent de l'expression. Y_comp — donc k, donc le point de fonctionnement — ne dépend QUE de la fraction de RÉSINE. Le partage fibres/charge n'a aucun effet, et l'incertitude sur le renfort mise en évidence à l'étape 1 est sans conséquence sur la réponse matériau.
A55: > | B55: Étape 6 — couplage et densités | I55: k = (ρ_v − ρ_c)/ρ_c = (1 − Y_comp)/Y_comp ; ρ_v = (1 − φ)/Σ_i (w_i/ρ_i)
B56: couplage k = B'g / B'c | C56: =(1-C53)/C53 -> 0.1816839 | I56: attendu 0.1817 — la SEULE grandeur qui distingue le MX-4926 du SC-1008
B57: porosité φ | C57: 0.02 | I57: contrôlée au §5 : c'est celle qui restitue la densité publiée
B58: volume de solide par kg [m³/kg] | C58: =C43/$C$29+D43/$C$30+E43/$C$31 -> 0.00067532573 | I58: Σ w_i/ρ_i
B59: ρ vierge [kg/m³] | C59: =(1-C57)/C58 -> 1451.1516 | I59: attendu 1451 (PICA : 274 · TACOT : 280 · CPh70 : 1465)
B60: ρ char [kg/m³] | C60: =C59*C53 -> 1228.037 | I60: attendu 1228
B61: gaz de pyrolyse libéré [kg/m³] | C61: =C59-C60 -> 223.11456 | I61: attendu 223.1
B62: … soit en % de la masse vierge | C62: =(1-C53)*100 -> 15.375 | I62: 15.4 % — contre 21.4 % pour le TACOT et 12.2 % pour le CPh70
B63: k est un rapport de MASSES : ni les densités ni la porosité n'y entrent — elles ne servent qu'à la récession ṡ = B'c·ṁe/ρ_c. C'est pourquoi l'incertitude sur ρ des constituants, réelle, ne se propage pas au point de fonctionnement.
A65: §4 — RÉSULTAT : CE QUI ENTRE DANS LE XML
B66: Composition élémentaire (fractions molaires) | C66: C | D66: H | E66: O | F66: Somme
B67: calcul — chaîne complète ci-dessus | C67: =C47 -> 0.25257099 | D67: =D47 -> 0.64065344 | E67: =E47 -> 0.10677557 | F67: =SUM(C67:E67) -> 1
B68: valeur portée dans le XML (mx4926_pyro) | C68: 0.2526 | D68: 0.6407 | E68: 0.1068 | F68: =SUM(C68:E68) -> 1.0001
B69: écart relatif |calcul − XML| / XML | C69: =ABS(C67-C68)/C68 -> 0.00011484491 | D69: =ABS(D67-D68)/D68 -> 7.2675212e-05 | E69: =ABS(E67-E68)/E68 -> 0.0002287188
B70: Char (mx4926_char) | C70: C | D70: H | E70: O
B71: composition du XML | C71: 1 | D71: — | E71: —
B72: Le fichier mx4926-air.xml est donc STRICTEMENT identique à sc1008-air.xml — même liste d'espèces, mêmes trois compositions. Il n'est justifié que par la traçabilité : nommer le matériau. Pour les propriétés du gaz de pyrolyse seul (h_g, Cp, M, γ), il n'y a pas non plus de fichier propre : sc1008-pyrogas.xml est valable tel quel.
A74: §5 — CONTRÔLES ET VALIDATION CROISÉE
A75: > | B75: Contrôle A — identité BIT À BIT de la table B' avec celle du SC-1008 | I75: diff caractère pour caractère de la sortie de `bprime`
B76: B'g testé | C76: lignes comparées | D76: lignes différentes
B77: 0 | C77: 149 | D77: 0
B78: 0.1 | C78: 149 | D78: 0
B79: 0.5 | C79: 149 | D79: 0
B80: 2 | C80: 149 | D80: 0
B81: Produit par `python mx4926_bprime/composition_mx4926_verification.py` §5. Pas « proche » : identique caractère pour caractère, comme cph70-air_25 face à tacot-air_25.
A82: > | B82: Contrôle B — limite d'oxydation à 300 K | I82: C + O2 → CO2, indépendante de la pression
B83: B'c(300 K, B'g = 0, 1 atm) | C83: 0.087427 | I83: attendu 0.0874 — une valeur ≈ 200 signalerait l'absence de C(gr)
A84: > | B84: Contrôle C — la porosité retenue restitue-t-elle la densité publiée ? | I84: φ = 1 − ρ_publié · Σ_i (w_i/ρ_i)
B85: porosité déduite de la densité publiée | C85: =1-C32*C58 -> 0.020777694 | I85: 0.0208 — à comparer au 0.02 retenu à l'étape 6 ; faible et positive, cohérent avec un composite dense pressé
B86: écart sur ρ_v | C86: =ABS(C59-C32)/C32 -> 0.00079419543 | I86: la porosité n'est donc pas un paramètre libre : elle est fixée par la densité mesurée
A87: > | B87: Contrôle D — le centroïde referme-t-il, et tombe-t-il dans les plages effectives ? | I87: marge = distance à la borne la plus proche ; elle doit être > 0
B88: défaut de fermeture |Σw − 1| | C88: =ABS(F43-1) -> 0 | I88: nul par construction : la charge est fermée par différence (étape 2)
B89: marge du renfort dans [min_eff ; max_eff] | C89: =MIN(C43-C37,D37-C43) -> 0.03797619 | I89: 0.0380 — le centroïde est loin des deux bornes
B90: marge de la matrice dans [min_eff ; max_eff] | C90: =MIN(D43-C38,D38-D43) -> 0.02833333 | I90: 0.0283 — idem
A92: §6 — SENSIBILITÉ : SEULE LA FRACTION DE RÉSINE COMPTE
B93: w_résine testé | C93: Y_comp | D93: k = B'g/B'c | E93: B'c stationnaire 1 atm 3000 K | F93: gaz — C | G93: gaz — H | H93: gaz — O
B94: 0.31 | C94: =1-(1-$C$28)*B94 -> 0.8605 | D94: =(1-C94)/C94 -> 0.16211505 | E94: 0.18171 | F94: =$C$47 -> 0.25257099 | G94: =$D$47 -> 0.64065344 | H94: =$E$47 -> 0.10677557
B95: 0.341667 | C95: =1-(1-$C$28)*B95 -> 0.84624985 | D95: =(1-C95)/C95 -> 0.18168411 | E95: 0.18187 | F95: =$C$47 -> 0.25257099 | G95: =$D$47 -> 0.64065344 | H95: =$E$47 -> 0.10677557
B96: 0.37 | C96: =1-(1-$C$28)*B96 -> 0.8335 | D96: =(1-C96)/C96 -> 0.19976005 | E96: 0.18203 | F96: =$C$47 -> 0.25257099 | G96: =$D$47 -> 0.64065344 | H96: =$E$47 -> 0.10677557
B97: Les trois dernières colonnes sont CONSTANTES : c'est la démonstration de cet onglet, comme pour le CPh70. Toute la plage de composition annoncée (31-37 % de résine) déplace k de 0.162 à 0.200 et ne touche pas d'un iota la composition portée dans le XML — ni, en pratique, le B'c stationnaire : 0.18 % d'étendue à 3000 K, 1.07 % à 2000 K, 4.6 % seulement au genou de sublimation à 3700 K. Ce n'est pas le paramètre à resserrer en priorité.
B98: Sensibilité au partage fibres/charge | C98: renfort | D98: charge | E98: Y_comp | F98: k
B99: w_résine gelé au centroïde | C99: 0.47 | D99: 0.189 | E99: =1-(1-$C$28)*$D$43 -> 0.84625 | F99: =(1-E99)/E99 -> 0.1816839
B100: w_résine gelé au centroïde | C100: 0.522024 | D100: 0.13631 | E100: =1-(1-$C$28)*$D$43 -> 0.84625 | F100: =(1-E100)/E100 -> 0.1816839
B101: w_résine gelé au centroïde | C101: 0.56 | D101: 0.098 | E101: =1-(1-$C$28)*$D$43 -> 0.84625 | F101: =(1-E101)/E101 -> 0.1816839
B102: Colonnes Y_comp et k STRICTEMENT constantes : déplacer 9 points de masse du renfort vers la charge ne change rien. Les deux sont du carbone à perte de masse nulle — seule leur SOMME compte, et la fermeture la fixe à 1 − w_résine. (Les couples ci-dessus ne referment volontairement pas à 1 avec w_résine : ils n'illustrent que le partage.)
A104: §7 — RÉPONSE MATÉRIAU (n'entre PAS dans le XML)
B105: Matériau | C105: k = B'g/B'c | D105: nature
B106: TACOT (10/10/80 vol.) | C106: ='TACOT'!C103 -> 0.27272727 | D106: poreux — beaucoup de résine par unité de masse
B107: PICA / SC-1008 | C107: ='SC-1008'!C126 -> 0.2345679 | D107: même résine, sans charge, taux de résine plus élevé
B108: MX-4926 | C108: =C56 -> 0.1816839 | D108: dense et chargé
...

Sheet Liège-phénolique
A1: Liège / phénolique (cork phenolic) — 80 / 20 en masse
A2: Le SEUL matériau du dépôt dont le RENFORT PYROLYSE AUSSI : le gaz est le mélange de deux gaz, et le rapport renfort/résine entre dans la table B'
A3: Fichier(s) XML : data/mixtures/cork-air.xml · cork-pyrogas.xml
A5: §0 — FICHE D'IDENTITÉ
B6: Matériau | C6: composite liège / résine phénolique, 80 % liège / 20 % résine en MASSE du solide | I6: matériau de type P50 (Amorim) — IXV et QARMAN
B7: Renfort | C7: liège (Quercus suber) — subérine 45 / lignine 27 / polysaccharides 12 / tanins 6 / céroïdes 6 % | I7: IL PYROLYSE : c'est l'essentiel du gaz produit
B8: Résine | C8: novolac C7H6O, rendement en char 50 % | I8: même motif que TACOT, PICA, CPh70
B9: Rendement en char du composite | C9: 20 % — mesuré par TGA sur le cork P50 (argon, 10 K/min, plateau 780-1650 K) | I9: Sakraker et al., CEAS Space Journal 14:377-393 (2022)
B10: Sources | C10: cork_bprime/mise_en_donnees_cork.md · cork_pyrolysis_data.py
B11: Compositions du XML | C11: air (-bl) · cork_pyro (-py) · cork_char (-char, -char-elem C)
A13: §1 — HYPOTHÈSES
A14: H1 | B14: LE RENFORT PYROLYSE. Le gaz est produit par les DEUX constituants, mélangés au prorata des masses réellement dégazées. | I14: C'est toute la différence avec un carbone/phénolique. Conséquence : le rapport liège/résine entre DANS la composition du gaz, donc dans la table B' — ce qui n'était pas le cas du CPh70.
A15: H2 | B15: « 80 % de liège » se lit en MASSE, pas en volume. | I15: Piège d'énoncé : le liège est très léger (≈ 120 kg/m³ contre 1200 pour la résine). 80 % en VOLUME ne ferait que 28.6 % en masse — un tout autre matériau (gaz C:0.277, char 39.3 %, k = 1.545).
A16: H3 | B16: Analyse élémentaire du liège retenue : C 62.4 / H 8.5 / O 28.4 % masse (littérature, sec sans cendres). | I16: PROVENANCE À CONFIRMER : valeurs usuelles pour Quercus suber, non vérifiées sur une source primaire accessible. Le contrôle biochimique du §5 est, lui, traçable ligne à ligne. L'azote (~0.6 %) est négligé — le retenir ajouterait une 4e composante au gaz.
A17: H4 | B17: Rendement en char du liège DÉDUIT du composite mesuré et de la résine : 0.80·y + 0.20·0.50 = 0.20 ⇒ y = 12.5 %. | I17: La TGA ne sépare pas les deux constituants. Lever l'hypothèse « résine à 50 % » demanderait une seconde TGA, sur la résine seule ou sur le liège seul.
A18: H5 | B18: Les deux constituants carbonisent vers du carbone pur ⇒ char C:1.0. | I18: Un char de liège réel retient un peu de H et de O : le §5 chiffre cette variante (char multi-élément C:0.864, H:0.108, O:0.027) — et rappelle qu'il faut alors RETIRER ces atomes du gaz.
A19: H6 | B19: Le couplage stationnaire se calcule sur les MASSES : k = (1 − y)/y = 4.0. | I19: L'identité k = (ρ_v − ρ_c)/ρ_c suppose un volume constant, que ce matériau ne respecte PAS : le char se rétracte (V_char/V_vierge ≈ 0.32). Les densités donneraient k = 0.61, six fois trop peu.
A21: §2 — DONNÉES D'ENTRÉE
A22: > | B22: Analyse élémentaire du liège — valeurs de littérature (RETENUES) | I22: % masse, sec sans cendres
C23: C | D23: H | E23: O | F23: Somme
B24: liège [% masse] | C24: 62.4 | D24: 8.5 | E24: 28.4 | F24: =SUM(C24:E24) -> 99.3
B25: La somme vaut 99.3 % et non 100 : l'étape 1 renormalise. C'est exactement ce que fait cork_pyrolysis_data.py.
A27: > | B27: Constituants biochimiques du liège et leurs unités de répétition (sert au contrôle du §5) | I27: M_i = Σ_E ν_E,i · M_E
B28: Constituant — unité de répétition | C28: % masse | D28: ν_C | E28: ν_H | F28: ν_O | G28: M [g/mol] | H28: rendement en char
B29: subérine — C57H104O12 (glycérol + 3 acides époxy-hydroxy C18, − 3 H2O) | C29: 45 | D29: 57 | E29: 104 | F29: 12 | G29: =D29*Constantes!$C$7+E29*Constantes!$C$8+F29*Constantes!$C$9 -> 981.447 | H29: 0.15
B30: lignine — C10H12O3 (alcool coniférylique, unité guaïacyle) | C30: 27 | D30: 10 | E30: 12 | F30: 3 | G30: =D30*Constantes!$C$7+E30*Constantes!$C$8+F30*Constantes!$C$9 -> 180.203 | H30: 0.45
B31: polysaccharides — C6H10O5 (anhydroglucose) | C31: 12 | D31: 6 | E31: 10 | F31: 5 | G31: =D31*Constantes!$C$7+E31*Constantes!$C$8+F31*Constantes!$C$9 -> 162.141 | H31: 0.15
B32: tanins — C15H14O6 (flavan-3-ol, catéchine) | C32: 6 | D32: 15 | E32: 14 | F32: 6 | G32: =D32*Constantes!$C$7+E32*Constantes!$C$8+F32*Constantes!$C$9 -> 290.271 | H32: 0.4
B33: céroïdes — C30H50O (friedéline) | C33: 6 | D33: 30 | E33: 50 | F33: 1 | G33: =D33*Constantes!$C$7+E33*Constantes!$C$8+F33*Constantes!$C$9 -> 426.729 | H33: 0.02
B34: SOMME des parts | C34: =SUM(C29:C33) -> 96
B35: Les parts somment à 96 % : le complément (cendres ~1 %, humidité résiduelle, extractibles mineurs) n'est pas de la matière C/H/O identifiée. On renormalise donc sur les 96 % déclarés. Les rendements en char par constituant (dernière colonne) sont des ordres de grandeur d'ATG lente sous inerte — ils servent au contrôle B du §5, pas au calcul du XML.
B37: fraction massique de liège dans le solide | C37: 0.8 | I37: hypothèse H2 — lecture MASSIQUE
B38: fraction massique de résine dans le solide | C38: =1-C37 -> 0.2
B39: rendement en char du COMPOSITE (mesuré, TGA P50) | C39: 0.2 | I39: plateau de 780 à 1650 K, argon, 10 K/min
B40: rendement en char de la RÉSINE | C40: 0.5 | I40: valeur classique novolac (énoncé) — même valeur que le TACOT
B41: motif de la résine — ν_C | C41: 7 | I41: novolac linéaire C7H6O, cf. Constantes §3
B42: ν_H | C42: 6
B43: ν_O | C43: 1
B44: ρ vierge / ρ char mesurés du P50 [kg/m³] | C44: 465.6 | I44: Sakraker et al. : 464.5 et 466.7 vierge
C45: 289.1 | I45: Sakraker et al. : 279.9 et 298.4 char — n'entre PAS dans k, cf. H6
A47: §3 — CALCUL PAS À PAS
A48: > | B48: Étape 1 — renormaliser l'analyse élémentaire du liège à 100 % | I48: w_E = w_E,brut / Σ w_j,brut
C49: C | D49: H | E49: O | F49: Somme
B50: liège renormalisé [% masse] | C50: =C24/$F$24*100 -> 62.839879 | D50: =D24/$F$24*100 -> 8.5599194 | E50: =E24/$F$24*100 -> 28.600201 | F50: =SUM(C50:E50) -> 100
A51: > | B51: Étape 2 — déduire le rendement en char du LIÈGE du rendement mesuré du composite | I51: w_liège·y_liège + w_résine·y_résine = y_composite
B52: y_liège = (y_comp − w_rés·y_rés) / w_liège | C52: =($C$39-$C$38*$C$40)/$C$37 -> 0.125 | I52: attendu 0.125 — c'est LE nombre déduit, et le plus incertain de la chaîne (§6)
A53: > | B53: Étape 3 — bilan de masse sur 100 g de composite vierge | I53: m_char,i = m_i · y_i ; m_gaz,i = m_i · (1 − y_i)
B54: Constituant | C54: masse [g] | D54: rendement char | E54: char [g] | F54: gaz [g]
B55: liège | C55: =$C$37*100 -> 80 | D55: =$C$52 -> 0.125 | E55: =C55*D55 -> 10 | F55: =C55-E55 -> 70
B56: résine | C56: =$C$38*100 -> 20 | D56: =$C$40 -> 0.5 | E56: =C56*D56 -> 10 | F56: =C56-E56 -> 10
B57: COMPOSITE | C57: =C55+C56 -> 100 | D57: =(E55+E56)/(C55+C56) -> 0.2 | E57: =E55+E56 -> 20 | F57: =F55+F56 -> 80
B58: Contrôle : la colonne « rendement char » du composite doit redonner exactement les 20 % mesurés — c'est la définition même de l'étape 2.
A59: > | B59: Étape 4 — fermeture élémentaire, constituant par constituant : aucun atome n'est créé | I59: n_E(gaz, i) = n_E(constituant, i) − n_E(char, i)
B60: Moles d'atomes | C60: C | D60: H | E60: O | F60: Somme | G60: x_E du gaz partiel
B61: liège — atomes du constituant | C61: =C55*C50/100/Constantes!$C$7 -> 4.1854886 | D61: =C55*D50/100/Constantes!$C$8 -> 6.7935869 | E61: =C55*E50/100/Constantes!$C$9 -> 1.4300995 | F61: =SUM(C61:E61) -> 12.409175
B62: liège — atomes du char (C pur) | C62: =E55/Constantes!$C$7 -> 0.83257014 | D62: 0 | E62: 0 | F62: =SUM(C62:E62) -> 0.83257014
B63: liège — GAZ = constituant − char | C63: =C61-C62 -> 3.3529184 | D63: =D61-D62 -> 6.7935869 | E63: =E61-E62 -> 1.4300995 | F63: =SUM(C63:E63) -> 11.576605 | G63: C:0.290 H:0.587 O:0.124
A64: > | B64: Étape 5 — même fermeture pour la résine (motif C7H6O) | I64: n_E = m_résine·ν_E / M_motif ; M_motif = Σ ν_E·M_E
B65: M du motif de résine [g/mol] | C65: =C41*Constantes!$C$7+C42*Constantes!$C$8+C43*Constantes!$C$9 -> 106.124 | I65: attendu 106.12 g/mol
B66: Moles d'atomes | C66: C | D66: H | E66: O | F66: Somme | G66: x_E du gaz partiel
B67: résine — atomes du constituant | C67: =C56/$C$65*$C$41 -> 1.3192115 | D67: =C56/$C$65*$C$42 -> 1.1307527 | E67: =C56/$C$65*$C$43 -> 0.18845878 | F67: =SUM(C67:E67) -> 2.638423
B68: résine — atomes du char (C pur) | C68: =E56/Constantes!$C$7 -> 0.83257014 | D68: 0 | E68: 0 | F68: =SUM(C68:E68) -> 0.83257014
B69: résine — GAZ = constituant − char | C69: =C67-C68 -> 0.48664134 | D69: =D67-D68 -> 1.1307527 | E69: =E67-E68 -> 0.18845878 | F69: =SUM(C69:E69) -> 1.8058528 | G69: C:0.269 H:0.626 O:0.104
A70: > | B70: Étape 6 — mélanger les deux gaz et normaliser | I70: n_E(gaz) = n_E(gaz, liège) + n_E(gaz, résine) ; x_E = n_E / Σ n_j
C71: C | D71: H | E71: O | F71: Somme | G71: M_gaz [g/mol] | H71: H/O
B72: gaz du composite — moles d'atomes | C72: =C63+C69 -> 3.8395598 | D72: =D63+D69 -> 7.9243396 | E72: =E63+E69 -> 1.6185582 | F72: =SUM(C72:E72) -> 13.382458
B73: x_E (fraction molaire élémentaire) | C73: =C72/$F$72 -> 0.28690992 | D73: =D72/$F$72 -> 0.59214382 | E73: =E72/$F$72 -> 0.12094626 | F73: =SUM(C73:E73) -> 1 | G73: =C73*Constantes!$C$7+D73*Constantes!$C$8+E73*Constantes!$C$9 -> 5.9779752 | H73: =D73/E73 -> 4.8959249
B74: y_E (fraction massique élémentaire) | C74: =C73*Constantes!$C$7/$G$73 -> 0.57646191 | D74: =D73*Constantes!$C$8/$G$73 -> 0.099846678 | E74: =E73*Constantes!$C$9/$G$73 -> 0.32369142 | F74: =SUM(C74:E74) -> 1
B75: H/O = 4.89 : bien plus bas que les 5.9-6.8 des phénoliques. C'est normal et attendu — le liège (subérine, lignine, polysaccharides) est nativement bien plus oxygéné qu'un phénolique. L'invariant H/O de l'onglet SC-1008 ne s'applique donc PAS à ce matériau.
A77: §4 — RÉSULTAT : CE QUI ENTRE DANS LE XML
B78: Composition élémentaire (fractions molaires) | C78: C | D78: H | E78: O | F78: Somme
B79: calcul — chaîne complète ci-dessus | C79: =C73 -> 0.28690992 | D79: =D73 -> 0.59214382 | E79: =E73 -> 0.12094626 | F79: =SUM(C79:E79) -> 1
B80: valeur portée dans le XML (cork_pyro) | C80: 0.287 | D80: 0.592 | E80: 0.121 | F80: =SUM(C80:E80) -> 1
B81: écart relatif |calcul − XML| / XML | C81: =ABS(C79-C80)/C80 -> 0.00031388124 | D81: =ABS(D79-D80)/D80 -> 0.00024294042 | E81: =ABS(E79-E80)/E80 -> 0.0004441059
B82: Char (cork_char) | C82: C | D82: H | E82: O
B83: composition du XML | C83: 1 | D83: — | E83: —
A85: §5 — CONTRÔLES ET VALIDATION CROISÉE
A86: > | B86: Contrôle A — reconstruire le liège depuis ses unités de répétition (traçable ligne à ligne) | I86: w_E = Σ_i (part_i / Σ parts) · (ν_E,i·M_E / M_i)
C87: C | D87: H | E87: O | F87: Somme | G87: écart / littérature [points]
B88: liège reconstruit [% masse] | C88: =SUMPRODUCT($C$29:$C$33,D29:D33/$G$29:$G$33)*Constantes!$C$7/$C$34*100 -> 66.157147 | D88: =SUMPRODUCT($C$29:$C$33,E29:E33/$G$29:$G$33)*Constantes!$C$8/$C$34*100 -> 8.7138926 | E88: =SUMPRODUCT($C$29:$C$33,F29:F33/$G$29:$G$33)*Constantes!$C$9/$C$34*100 -> 25.12896 | F88: =SUM(C88:E88) -> 100 | G88: =MAX(ABS(C88-C50),ABS(D88-D50),ABS(E88-E50)) -> 3.4712412
B89: Attendu C 66.16 / H 8.71 / O 25.13. L'hydrogène tombe à 0.2 point près ; le carbone est surestimé d'environ 4 points et l'oxygène sous-estimé d'autant. Deux causes non exclusives : (a) les 4 % manquants, s'ils sont de la matière oxygénée, rapprocheraient la reconstruction à ~1 point ; (b) l'unité choisie pour la subérine, qui pèse 45 % à elle seule. Effet sur le gaz : C:0.300 / H:0.594 / O:0.107 au lieu de C:0.287 / H:0.592 / O:0.121 — réel, mais du second ordre devant l'incertitude sur le rendement en char (§6).
A90: > | B90: Contrôle B — rendement en char du liège par additivité des constituants | I90: y_liège = Σ_i part_i · y_i / Σ parts
B91: y_liège par additivité | C91: =SUMPRODUCT($C$29:$C$33,$H$29:$H$33)/$C$34 -> 0.241875 | I91: attendu 24.2 % — contre 12.5 % déduit de la TGA du composite
B92: ⇒ rendement du composite impliqué | C92: =$C$37*C91+$C$38*$C$40 -> 0.2935 | I92: 29.3 % contre 20.0 % mesurés sur le P50 : les deux voies NE SE REJOIGNENT PAS, d'un facteur deux sur le liège
B93: On garde la MESURE. Explications de l'écart : le P50 est plastifié au glycol, qui part entièrement en gaz ; son rapport liège/résine n'est pas nécessairement 80/20 ; et les rendements par constituant ci-dessus sont indicatifs. C'est la mesure qui fixe k, la grandeur qui gouverne le point de fonctionnement.
A94: > | B94: Contrôle C — variante : char de liège retenant H et O (char multi-élément) | I94: n_E(char) = Σ_i (m_char,i / M_i) · ν_E,i
B95: char de liège supposé [% masse] | C95: C | D95: H | E95: O | F95: Somme
B96: hypothèse de travail | C96: 90 | D96: 2 | E96: 8 | F96: =SUM(C96:E96) -> 100
B97: moles d'atomes du char total (liège + résine) | C97: =E55*C96/100/Constantes!$C$7+E56/Constantes!$C$7 -> 1.5818833 | D97: =E55*D96/100/Constantes!$C$8 -> 0.1984127 | E97: =E55*E96/100/Constantes!$C$9 -> 0.050003125 | F97: =SUM(C97:E97) -> 1.8302991
B98: ⇒ cork_char multi-élément (x_E) | C98: =C97/$F$97 -> 0.86427583 | D98: =D97/$F$97 -> 0.10840452 | E98: =E97/$F$97 -> 0.027319647 | F98: =SUM(C98:E98) -> 1
B99: Attendu C:0.864, H:0.108, O:0.027. `-char-elem C` reste valable : l'élément du bilan doit être présent dans le char et absent (ou minoritaire) au bord de couche limite. ATTENTION À LA COHÉRENCE : si le char retient des atomes, il faut les RETIRER du gaz (le gaz devient C:0.297, H:0.585, O:0.119). C'est automatique dans la fermeture élémentaire, pas si l'on recopie deux compositions de sources différentes.
A101: §6 — SENSIBILITÉ
A102: > | B102: Au rendement en char du liège — LE paramètre à mesurer en priorité
B103: y_liège testé | C103: C | D103: H | E103: O | F103: y composite impliqué | G103: k = (1−y)/y
B104: 0.05 | C104: =($C$61-$C$55*B104/Constantes!$C$7+$C$69)/(($C$61-$C$55*B104/Constantes!$C$7+$C$69)+($D$61+$D$69)+($E$61+$E$69)) -> 0.31257038 | D104: =($D$61+$D$69)/(($C$61-$C$55*B104/Constantes!$C$7+$C$69)+($D$61+$D$69)+($E$61+$E$69)) -> 0.5708356 | E104: =($E$61+$E$69)/(($C$61-$C$55*B104/Constantes!$C$7+$C$69)+($D$61+$D$69)+($E$61+$E$69)) -> 0.11659403 | F104: =$C$37*B104+$C$38*$C$40 -> 0.14 | G104: =(1-F104)/F104 -> 6.1428571
B105: 0.1 | C105: =($C$61-$C$55*B105/Constantes!$C$7+$C$69)/(($C$61-$C$55*B105/Constantes!$C$7+$C$69)+($D$61+$D$69)+($E$61+$E$69)) -> 0.29567364 | D105: =($D$61+$D$69)/(($C$61-$C$55*B105/Constantes!$C$7+$C$69)+($D$61+$D$69)+($E$61+$E$69)) -> 0.5848665 | E105: =($E$61+$E$69)/(($C$61-$C$55*B105/Constantes!$C$7+$C$69)+($D$61+$D$69)+($E$61+$E$69)) -> 0.11945986 | F105: =$C$37*B105+$C$38*$C$40 -> 0.18 | G105: =(1-F105)/F105 -> 4.5555556
B106: 0.125 | C106: =($C$61-$C$55*B106/Constantes!$C$7+$C$69)/(($C$61-$C$55*B106/Constantes!$C$7+$C$69)+($D$61+$D$69)+($E$61+$E$69)) -> 0.28690992 | D106: =($D$61+$D$69)/(($C$61-$C$55*B106/Constantes!$C$7+$C$69)+($D$61+$D$69)+($E$61+$E$69)) -> 0.59214382 | E106: =($E$61+$E$69)/(($C$61-$C$55*B106/Constantes!$C$7+$C$69)+($D$61+$D$69)+($E$61+$E$69)) -> 0.12094626 | F106: =$C$37*B106+$C$38*$C$40 -> 0.2 | G106: =(1-F106)/F106 -> 4
B107: 0.15 | C107: =($C$61-$C$55*B107/Constantes!$C$7+$C$69)/(($C$61-$C$55*B107/Constantes!$C$7+$C$69)+($D$61+$D$69)+($E$61+$E$69)) -> 0.27792535 | D107: =($D$61+$D$69)/(($C$61-$C$55*B107/Constantes!$C$7+$C$69)+($D$61+$D$69)+($E$61+$E$69)) -> 0.59960453 | E107: =($E$61+$E$69)/(($C$61-$C$55*B107/Constantes!$C$7+$C$69)+($D$61+$D$69)+($E$61+$E$69)) -> 0.12247012 | F107: =$C$37*B107+$C$38*$C$40 -> 0.22 | G107: =(1-F107)/F107 -> 3.5454545
B108: 0.2 | C108: =($C$61-$C$55*B108/Constantes!$C$7+$C$69)/(($C$61-$C$55*B108/Constantes!$C$7+$C$69)+($D$61+$D$69)+($E$61+$E$69)) -> 0.25925946 | D108: =($D$61+$D$69)/(($C$61-$C$55*B108/Constantes!$C$7+$C$69)+($D$61+$D$69)+($E$61+$E$69)) -> 0.61510452 | E108: =($E$61+$E$69)/(($C$61-$C$55*B108/Constantes!$C$7+$C$69)+($D$61+$D$69)+($E$61+$E$69)) -> 0.12563602 | F108: =$C$37*B108+$C$38*$C$40 -> 0.26 | G108: =(1-F108)/F108 -> 2.8461538
B109: 0.242 | C109: =($C$61-$C$55*B109/Constantes!$C$7+$C$69)/(($C$61-$C$55*B109/Constantes!$C$7+$C$69)+($D$61+$D$69)+($E$61+$E$69)) -> 0.24281777 | D109: =($D$61+$D$69)/(($C$61-$C$55*B109/Constantes!$C$7+$C$69)+($D$61+$D$69)+($E$61+$E$69)) -> 0.62875755 | E109: =($E$61+$E$69)/(($C$61-$C$55*B109/Constantes!$C$7+$C$69)+($D$61+$D$69)+($E$61+$E$69)) -> 0.12842467 | F109: =$C$37*B109+$C$38*$C$40 -> 0.2936 | G109: =(1-F109)/F109 -> 2.4059946
...

Sheet Chêne
A1: Bois de chêne — ablateur pyrolysant à un seul constituant
A2: Le cas le plus simple des ablateurs pyrolysants : TOUT le solide pyrolyse, sans résine ni renfort inerte — une seule fermeture élémentaire bois − char
A3: Fichier(s) XML : data/mixtures/oak-air.xml · oak-pyrogas.xml
A5: §0 — FICHE D'IDENTITÉ
B6: Matériau | C6: bois de chêne massif (Quercus robur / Q. petraea), SEC, sans résine | I6: feuillu — à ne pas confondre avec le liège (Q. suber)
B7: Constituants | C7: cellulose 43 / hémicelluloses 22 / lignine S+G 25 / ellagitanins 8 % | I7: IL PYROLYSE ENTIÈREMENT : 80 % du bois part en gaz
B8: Rendement en char | C8: 20 % en masse | I8: donnée de l'énoncé
B9: Unité de répétition globale | C9: C6H8.7O3.95 — soit CH1.45O0.66 par atome de carbone | I9: calculée à l'étape 5 du §3
B10: Sources | C10: oak_bprime/mise_en_donnees_chene.md · oak_pyrolysis_data.py
B11: Compositions du XML | C11: air (-bl) · oak_pyro (-py) · oak_char (-char, -char-elem C)
A13: §1 — HYPOTHÈSES
A14: H1 | B14: UN SEUL CONSTITUANT, QUI PYROLYSE ENTIÈREMENT. Gaz = bois − char, sans mélange de gaz. | I14: Route C (fermeture élémentaire), mais partant d'une ANALYSE élémentaire et non d'un motif idéalisé. Pas de rapport renfort/résine : contrairement au liège, rien d'autre que le rendement en char ne pondère le gaz.
A15: H2 | B15: Bois SEC. L'humidité (8-12 % dans un bois stabilisé à l'air) n'est pas comptée. | I15: Elle partirait intégralement en vapeur d'eau, donc dans le gaz : le §6 chiffre la variante (gaz plus riche en H et O, k plus grand).
A16: H3 | B16: Analyse élémentaire du chêne retenue : C 50.0 / H 6.1 / O 43.9 % masse (littérature, sec sans cendres). | I16: PROVENANCE À CONFIRMER : valeurs usuelles pour le bois de chêne, non vérifiées sur une source primaire accessible. Le contrôle biochimique du §5 les retrouve à 0.4 point près. L'azote (0.1-0.3 %) est négligé.
A17: H4 | B17: Rendement en char : 20 % en masse du bois sec. | I17: Donnée de l'énoncé. C'est LE paramètre du calcul : il fixe à la fois le carbone du gaz et le couplage k (§6). Le contrôle par additivité des constituants donne 22 %.
A18: H5 | B18: Le bois carbonise vers du carbone pur ⇒ char C:1.0. | I18: Un charbon de bois réel retient H et O (d'autant plus que la carbonisation est froide) : le §5 chiffre la variante — et rappelle qu'il faut alors RETIRER ces atomes du gaz.
A19: H6 | B19: Le couplage stationnaire se calcule sur les MASSES : k = (1 − y)/y = 4.0. | I19: L'identité k = (ρ_v − ρ_c)/ρ_c suppose un volume constant ; le bois se rétracte en carbonisant (retrait volumique typiquement 30-50 %).
A21: §2 — DONNÉES D'ENTRÉE
A22: > | B22: Analyse élémentaire du chêne — valeurs de littérature (RETENUES) | I22: % masse, sec sans cendres
C23: C | D23: H | E23: O | F23: Somme
B24: chêne [% masse] | C24: 50 | D24: 6.1 | E24: 43.9 | F24: =SUM(C24:E24) -> 100
B25: La somme vaut 100 % : l'étape 1 renormalise quand même, pour qu'une analyse mesurée (qui ne somme jamais exactement à 100) puisse être collée ici telle quelle.
A27: > | B27: Constituants biochimiques du chêne et leurs unités de répétition (sert au contrôle du §5) | I27: M_i = Σ_E ν_E,i · M_E
B28: Constituant — unité de répétition | C28: % masse | D28: ν_C | E28: ν_H | F28: ν_O | G28: M [g/mol] | H28: rendement en char
B29: cellulose — C6H10O5 (anhydroglucose) | C29: 43 | D29: 6 | E29: 10 | F29: 5 | G29: =D29*Constantes!$C$7+E29*Constantes!$C$8+F29*Constantes!$C$9 -> 162.141 | H29: 0.1
B30: hémicelluloses — C5H8O4 (anhydroxylose, glucuronoxylane) | C30: 22 | D30: 5 | E30: 8 | F30: 4 | G30: =D30*Constantes!$C$7+E30*Constantes!$C$8+F30*Constantes!$C$9 -> 132.115 | H30: 0.2
B31: lignine S — C11H14O4 (alcool sinapylique) | C31: 16 | D31: 11 | E31: 14 | F31: 4 | G31: =D31*Constantes!$C$7+E31*Constantes!$C$8+F31*Constantes!$C$9 -> 210.229 | H31: 0.35
B32: lignine G — C10H12O3 (alcool coniférylique) | C32: 9 | D32: 10 | E32: 12 | F32: 3 | G32: =D32*Constantes!$C$7+E32*Constantes!$C$8+F32*Constantes!$C$9 -> 180.203 | H32: 0.45
B33: tanins — C41H26O26 (vescalagine, ellagitanin) | C33: 8 | D33: 41 | E33: 26 | F33: 26 | G33: =D33*Constantes!$C$7+E33*Constantes!$C$8+F33*Constantes!$C$9 -> 934.633 | H33: 0.4
B34: SOMME des parts | C34: =SUM(C29:C33) -> 98
B35: Les parts somment à 98 % : le complément (cendres ~0.4 %, groupes acétyles des hémicelluloses, extractibles mineurs) n'est pas de la matière C/H/O identifiée. On renormalise sur les 98 % déclarés. La lignine de feuillu est répartie en 16 % S + 9 % G en masse, soit S/G = 1.52 en moles. Les rendements en char par constituant (dernière colonne) sont des ordres de grandeur d'ATG lente sous inerte — ils servent au contrôle B du §5, pas au calcul du XML.
B37: rendement en char du bois sec | C37: 0.2 | I37: hypothèse H4 — donnée de l'énoncé
B38: ρ vierge [kg/m³] | C38: 700 | I38: chêne sec, ordre de grandeur 650-750 kg/m³ — n'entre PAS dans le XML
B39: V_char / V_vierge (retrait volumique) | C39: 0.55 | I39: HYPOTHÈSE, non mesurée ici — à remplacer par une mesure (§7)
A41: §3 — CALCUL PAS À PAS
A42: > | B42: Étape 1 — renormaliser l'analyse élémentaire du chêne à 100 % | I42: w_E = w_E,brut / Σ w_j,brut
C43: C | D43: H | E43: O | F43: Somme
B44: chêne renormalisé [% masse] | C44: =C24/$F$24*100 -> 50 | D44: =D24/$F$24*100 -> 6.1 | E44: =E24/$F$24*100 -> 43.9 | F44: =SUM(C44:E44) -> 100
A45: > | B45: Étape 2 — bilan de masse sur 100 g de bois sec | I45: m_char = 100 · y ; m_gaz = 100 · (1 − y)
C46: masse [g] | D46: rendement char | E46: char [g] | F46: gaz [g]
B47: bois sec | C47: 100 | D47: =$C$37 -> 0.2 | E47: =C47*D47 -> 20 | F47: =C47-E47 -> 80
A48: > | B48: Étape 3 — fermeture élémentaire : aucun atome n'est créé | I48: n_E(gaz) = n_E(bois) − n_E(char)
B49: Moles d'atomes | C49: C | D49: H | E49: O | F49: Somme
B50: bois — atomes du solide vierge | C50: =$C$47*C44/100/Constantes!$C$7 -> 4.1628507 | D50: =$C$47*D44/100/Constantes!$C$8 -> 6.0515873 | E50: =$C$47*E44/100/Constantes!$C$9 -> 2.7439215 | F50: =SUM(C50:E50) -> 12.95836
B51: bois — atomes du char (C pur) | C51: =$E$47/Constantes!$C$7 -> 1.6651403 | D51: 0 | E51: 0 | F51: =SUM(C51:E51) -> 1.6651403
B52: GAZ = bois − char | C52: =C50-C51 -> 2.4977104 | D52: =D50-D51 -> 6.0515873 | E52: =E50-E51 -> 2.7439215 | F52: =SUM(C52:E52) -> 11.293219
B53: Le char ne prend que du carbone : tout l'hydrogène et tout l'oxygène du bois passent dans le gaz. Le char emporte 1.665 des 4.163 moles de carbone, soit 40 % du carbone du bois.
A54: > | B54: Étape 4 — normaliser | I54: x_E = n_E / Σ n_j ; y_E = x_E·M_E / Σ x_j·M_j
C55: C | D55: H | E55: O | F55: Somme | G55: M par atome [g/mol] | H55: H/O
B56: x_E (fraction molaire élémentaire) | C56: =C52/$F$52 -> 0.22116904 | D56: =D52/$F$52 -> 0.53586025 | E56: =E52/$F$52 -> 0.24297071 | F56: =SUM(C56:E56) -> 1 | G56: =C56*Constantes!$C$7+D56*Constantes!$C$8+E56*Constantes!$C$9 -> 7.0838968 | H56: =D56/E56 -> 2.2054521
B57: y_E (fraction massique élémentaire) | C57: =C56*Constantes!$C$7/$G$56 -> 0.375 | D57: =D56*Constantes!$C$8/$G$56 -> 0.07625 | E57: =E56*Constantes!$C$9/$G$56 -> 0.54875 | F57: =SUM(C57:E57) -> 1
B58: H/O = 2.2 : trois fois plus bas que les phénoliques (5.9-6.8) et deux fois plus bas que le liège (4.9). C'est le gaz le plus OXYGÉNÉ du dépôt — le bois est pour les deux tiers des polysaccharides, eux-mêmes à H/O = 2. Plus d'oxygène dans le gaz de pyrolyse, c'est plus d'oxydant disponible à la paroi pour le char.
A59: > | B59: Étape 5 — unité de répétition globale du bois (ramenée à 6 atomes de carbone) | I59: ν_E = 6 · (w_E/M_E) / (w_C/M_C)
C60: ν_C | D60: ν_H | E60: ν_O | F60: M [g/mol] | G60: H/C | H60: O/C
B61: bois de chêne — C6HxOy | C61: 6 | D61: =6*(D44/Constantes!$C$8)/(C44/Constantes!$C$7) -> 8.7222738 | E61: =6*(E44/Constantes!$C$9)/(C44/Constantes!$C$7) -> 3.9548689 | F61: =C61*Constantes!$C$7+D61*Constantes!$C$8+E61*Constantes!$C$9 -> 144.132 | G61: =D61/C61 -> 1.4537123 | H61: =E61/C61 -> 0.65914482
B62: Attendu C6H8.72O3.95 (M = 144.1 g/mol), soit CH1.45O0.66 : l'anhydroglucose C6H10O5 (cellulose) « enrichi en carbone » par la lignine. Cette unité n'entre pas dans le XML — c'est la même information que l'analyse élémentaire, écrite en motif.
A64: §4 — RÉSULTAT : CE QUI ENTRE DANS LE XML
B65: Composition élémentaire (fractions molaires) | C65: C | D65: H | E65: O | F65: Somme
B66: calcul — chaîne complète ci-dessus | C66: =C56 -> 0.22116904 | D66: =D56 -> 0.53586025 | E66: =E56 -> 0.24297071 | F66: =SUM(C66:E66) -> 1
B67: valeur portée dans le XML (oak_pyro) | C67: 0.221 | D67: 0.536 | E67: 0.243 | F67: =SUM(C67:E67) -> 1
B68: écart relatif |calcul − XML| / XML | C68: =ABS(C66-C67)/C67 -> 0.00076487757 | D68: =ABS(D66-D67)/D67 -> 0.00026072392 | E68: =ABS(E66-E67)/E67 -> 0.00012053466
B69: Char (oak_char) | C69: C | D69: H | E69: O
B70: composition du XML | C70: 1 | D70: — | E70: —
A72: §5 — CONTRÔLES ET VALIDATION CROISÉE
A73: > | B73: Contrôle A — reconstruire le chêne depuis ses unités de répétition (traçable ligne à ligne) | I73: w_E = Σ_i (part_i / Σ parts) · (ν_E,i·M_E / M_i)
C74: C | D74: H | E74: O | F74: Somme | G74: écart / littérature [points]
B75: chêne reconstruit [% masse] | C75: =SUMPRODUCT($C$29:$C$33,D29:D33/$G$29:$G$33)*Constantes!$C$7/$C$34*100 -> 50.38951 | D75: =SUMPRODUCT($C$29:$C$33,E29:E33/$G$29:$G$33)*Constantes!$C$8/$C$34*100 -> 6.0393205 | E75: =SUMPRODUCT($C$29:$C$33,F29:F33/$G$29:$G$33)*Constantes!$C$9/$C$34*100 -> 43.57117 | F75: =SUM(C75:E75) -> 100 | G75: =MAX(ABS(C75-C44),ABS(D75-D44),ABS(E75-E44)) -> 0.38950995
B76: ⇒ gaz de pyrolyse avec le chêne reconstruit (x_E) | C76: =(100*C75/$F$75/Constantes!$C$7-$E$47/Constantes!$C$7)/(100*C75/$F$75/Constantes!$C$7-$E$47/Constantes!$C$7+100*D75/$F$75/Constantes!$C$8+100*E75/$F$75/Constantes!$C$9) -> 0.22500337 | D76: =(100*D75/$F$75/Constantes!$C$8)/(100*C75/$F$75/Constantes!$C$7-$E$47/Constantes!$C$7+100*D75/$F$75/Constantes!$C$8+100*E75/$F$75/Constantes!$C$9) -> 0.5328096 | E76: =(100*E75/$F$75/Constantes!$C$9)/(100*C75/$F$75/Constantes!$C$7-$E$47/Constantes!$C$7+100*D75/$F$75/Constantes!$C$8+100*E75/$F$75/Constantes!$C$9) -> 0.24218703 | F76: =SUM(C76:E76) -> 1
B77: Attendu C 50.39 / H 6.04 / O 43.57, soit un gaz C:0.225 / H:0.533 / O:0.242. La reconstruction retombe sur l'analyse de littérature à 0.4 point près — bien mieux que pour le liège (4 points sur C) : l'unité dominante, l'anhydroglucose, est exacte, et il n'y a pas de subérine dont l'unité serait incertaine. L'écart sur le gaz (0.004 sur x_C) est négligeable.
A78: > | B78: Contrôle B — rendement en char par additivité des constituants | I78: y = Σ_i part_i · y_i / Σ parts
B79: y_chêne par additivité | C79: =SUMPRODUCT($C$29:$C$33,$H$29:$H$33)/$C$34 -> 0.21989796 | I79: attendu 22.0 % — contre 20 % retenus : les deux voies sont COHÉRENTES
B80: La cellulose, qui pèse 43 %, se dépolymérise en lévoglucosane et laisse peu de char ; la lignine et les tanins, aromatiques, en laissent le plus. Le rendement réel dépend fortement de la vitesse de chauffe : 20 % correspond à une pyrolyse lente, une pyrolyse flash descend vers 10-15 %.
A81: > | B81: Contrôle C — variante : char retenant H et O (char multi-élément) | I81: n_E(char) = m_char · w_E,char / M_E ; n_E(gaz) = n_E(bois) − n_E(char)
B82: char supposé [% masse] | C82: C | D82: H | E82: O | F82: Somme
B83: hypothèse de travail | C83: 90 | D83: 2 | E83: 8 | F83: =SUM(C83:E83) -> 100
B84: moles d'atomes du char | C84: =$E$47*C83/100/Constantes!$C$7 -> 1.4986263 | D84: =$E$47*D83/100/Constantes!$C$8 -> 0.3968254 | E84: =$E$47*E83/100/Constantes!$C$9 -> 0.10000625 | F84: =SUM(C84:E84) -> 1.9954579
B85: ⇒ oak_char multi-élément (x_E) | C85: =C84/$F$84 -> 0.75101873 | D85: =D84/$F$84 -> 0.19886433 | E85: =E84/$F$84 -> 0.050116943 | F85: =SUM(C85:E85) -> 1
B86: ⇒ gaz cohérent (x_E) | C86: =(C50-C84)/($F$50-$F$84) -> 0.24302183 | D86: =(D50-D84)/($F$50-$F$84) -> 0.51580887 | E86: =(E50-E84)/($F$50-$F$84) -> 0.24116929 | F86: =SUM(C86:E86) -> 1
B87: Attendu char C:0.751, H:0.199, O:0.050 et gaz C:0.243, H:0.516, O:0.241. `-char-elem C` reste valable. Un char qui retient H et O laisse PLUS de carbone au gaz (x_C +0.022) : c'est automatique dans la fermeture élémentaire, pas si l'on recopie deux compositions de sources différentes.
A89: §6 — SENSIBILITÉ
A90: > | B90: Au rendement en char — LE paramètre du calcul
B91: y testé | C91: C | D91: H | E91: O | G91: k = (1−y)/y
B92: 0.1 | C92: =($C$50-100*B92/Constantes!$C$7)/(($C$50-100*B92/Constantes!$C$7)+$D$50+$E$50) -> 0.27464444 | D92: =$D$50/(($C$50-100*B92/Constantes!$C$7)+$D$50+$E$50) -> 0.49906749 | E92: =$E$50/(($C$50-100*B92/Constantes!$C$7)+$D$50+$E$50) -> 0.22628807 | G92: =(1-B92)/B92 -> 9
B93: 0.15 | C93: =($C$50-100*B93/Constantes!$C$7)/(($C$50-100*B93/Constantes!$C$7)+$D$50+$E$50) -> 0.24885729 | D93: =$D$50/(($C$50-100*B93/Constantes!$C$7)+$D$50+$E$50) -> 0.51680986 | E93: =$E$50/(($C$50-100*B93/Constantes!$C$7)+$D$50+$E$50) -> 0.23433285 | G93: =(1-B93)/B93 -> 5.6666667
B94: 0.2 | C94: =($C$50-100*B94/Constantes!$C$7)/(($C$50-100*B94/Constantes!$C$7)+$D$50+$E$50) -> 0.22116904 | D94: =$D$50/(($C$50-100*B94/Constantes!$C$7)+$D$50+$E$50) -> 0.53586025 | E94: =$E$50/(($C$50-100*B94/Constantes!$C$7)+$D$50+$E$50) -> 0.24297071 | G94: =(1-B94)/B94 -> 4
B95: 0.25 | C95: =($C$50-100*B95/Constantes!$C$7)/(($C$50-100*B95/Constantes!$C$7)+$D$50+$E$50) -> 0.1913614 | D95: =$D$50/(($C$50-100*B95/Constantes!$C$7)+$D$50+$E$50) -> 0.55636885 | E95: =$E$50/(($C$50-100*B95/Constantes!$C$7)+$D$50+$E$50) -> 0.25226975 | G95: =(1-B95)/B95 -> 3
B96: 0.3 | C96: =($C$50-100*B96/Constantes!$C$7)/(($C$50-100*B96/Constantes!$C$7)+$D$50+$E$50) -> 0.15918135 | D96: =$D$50/(($C$50-100*B96/Constantes!$C$7)+$D$50+$E$50) -> 0.57850973 | E96: =$E$50/(($C$50-100*B96/Constantes!$C$7)+$D$50+$E$50) -> 0.26230891 | G96: =(1-B96)/B96 -> 2.3333333
B97: ±5 points de rendement déplacent le carbone du gaz de ∓0.03 et k de 3.0 à 5.7. Comme pour le liège, le rendement pèse bien plus sur la QUANTITÉ de gaz (k) que sur sa composition.
A98: > | B98: À l'humidité du bois — l'eau part entièrement dans le gaz | I98: m_eau = 100·h/(1−h) ; n_H += 2·n_eau ; n_O += n_eau
B99: humidité h (base humide) | C99: C | D99: H | E99: O | F99: char / bois humide | G99: k = m_gaz/m_char
B100: 0 | C100: =$C$52/($C$52+($D$52+2*(100*B100/(1-B100)/(2*Constantes!$C$8+Constantes!$C$9)))+($E$52+(100*B100/(1-B100)/(2*Constantes!$C$8+Constantes!$C$9)))) -> 0.22116904 | D100: =($D$52+2*(100*B100/(1-B100)/(2*Constantes!$C$8+Constantes!$C$9)))/($C$52+($D$52+2*(100*B100/(1-B100)/(2*Constantes!$C$8+Constantes!$C$9)))+($E$52+(100*B100/(1-B100)/(2*Constantes!$C$8+Constantes!$C$9)))) -> 0.53586025 | E100: =($E$52+(100*B100/(1-B100)/(2*Constantes!$C$8+Constantes!$C$9)))/($C$52+($D$52+2*(100*B100/(1-B100)/(2*Constantes!$C$8+Constantes!$C$9)))+($E$52+(100*B100/(1-B100)/(2*Constantes!$C$8+Constantes!$C$9)))) -> 0.24297071 | F100: =$E$47/(100+100*B100/(1-B100)) -> 0.2 | G100: =($F$47+100*B100/(1-B100))/$E$47 -> 4
B101: 0.08 | C101: =$C$52/($C$52+($D$52+2*(100*B101/(1-B101)/(2*Constantes!$C$8+Constantes!$C$9)))+($E$52+(100*B101/(1-B101)/(2*Constantes!$C$8+Constantes!$C$9)))) -> 0.19603281 | D101: =($D$52+2*(100*B101/(1-B101)/(2*Constantes!$C$8+Constantes!$C$9)))/($C$52+($D$52+2*(100*B101/(1-B101)/(2*Constantes!$C$8+Constantes!$C$9)))+($E$52+(100*B101/(1-B101)/(2*Constantes!$C$8+Constantes!$C$9)))) -> 0.55072662 | E101: =($E$52+(100*B101/(1-B101)/(2*Constantes!$C$8+Constantes!$C$9)))/($C$52+($D$52+2*(100*B101/(1-B101)/(2*Constantes!$C$8+Constantes!$C$9)))+($E$52+(100*B101/(1-B101)/(2*Constantes!$C$8+Constantes!$C$9)))) -> 0.25324057 | F101: =$E$47/(100+100*B101/(1-B101)) -> 0.184 | G101: =($F$47+100*B101/(1-B101))/$E$47 -> 4.4347826
B102: 0.12 | C102: =$C$52/($C$52+($D$52+2*(100*B102/(1-B102)/(2*Constantes!$C$8+Constantes!$C$9)))+($E$52+(100*B102/(1-B102)/(2*Constantes!$C$8+Constantes!$C$9)))) -> 0.18414188 | D102: =($D$52+2*(100*B102/(1-B102)/(2*Constantes!$C$8+Constantes!$C$9)))/($C$52+($D$52+2*(100*B102/(1-B102)/(2*Constantes!$C$8+Constantes!$C$9)))+($E$52+(100*B102/(1-B102)/(2*Constantes!$C$8+Constantes!$C$9)))) -> 0.55775929 | E102: =($E$52+(100*B102/(1-B102)/(2*Constantes!$C$8+Constantes!$C$9)))/($C$52+($D$52+2*(100*B102/(1-B102)/(2*Constantes!$C$8+Constantes!$C$9)))+($E$52+(100*B102/(1-B102)/(2*Constantes!$C$8+Constantes!$C$9)))) -> 0.25809883 | F102: =$E$47/(100+100*B102/(1-B102)) -> 0.176 | G102: =($F$47+100*B102/(1-B102))/$E$47 -> 4.6818182
B103: Un bois stabilisé à l'air (12 %) donne un gaz C:0.184 et k = 4.68 : l'effet sur la composition dépasse celui de ±5 points de rendement. Préciser « sec » ou « à X % d'humidité » dans l'énoncé.
A105: §7 — RÉPONSE MATÉRIAU (n'entre PAS dans le XML)
B106: k = B'g/B'c = m_gaz / m_char = (1 − y)/y | C106: =F47/E47 -> 4 | I106: attendu 4.0 — le même que le liège/phénolique, QUINZE FOIS le TACOT (0.273)
B107: ρ char [kg/m³] = y · ρ_v / (V_char/V_v) | C107: =$C$37*C38/C39 -> 254.54545 | I107: ≈ 255 kg/m³ avec le retrait supposé — à MESURER
B108: k si l'on prenait les densités : (ρ_v − ρ_c)/ρ_c | C108: =(C38-C107)/C107 -> 1.75 | I108: 1.75 — plus de deux fois trop peu : l'identité suppose un volume constant
B109: Conséquences pratiques : (1) balayer B'g jusqu'à ~10 (les tables oak_bprime vont à B'g = 5 et le balayage du point de fonctionnement à 10) ; (2) la récession se lit sur la ρ_char MESURÉE, pas sur 0.20·ρ_v = 140 kg/m³ ; (3) le gaz porte plus d'oxygène que de carbone (O/C = 1.10) : au-dessus de ~1500 K il OXYDE le char, et B'c CROÎT avec B'g (1 atm, 3000 K : 0.177 à B'g = 0, 0.79 à B'g = 5) — l'inverse du liège, dont le soufflage protège le char. Point de fonctionnement à 1 atm : B'c = 0.127 / 0.213 / 0.430 à 1000 / 2000 / 3000 K (oak_bprime).
A111: §8 — BLOC XML
...

Sheet Carbone
A1: Carbone graphite — ablateur non pyrolysant
A2: Cas dégénéré : le solide EST le char, il n'y a pas de gaz de pyrolyse · sert de cas de référence physique aux autres onglets
A3: Fichier(s) XML : data/mixtures/carbon-air.xml
A5: §0 — FICHE D'IDENTITÉ
B6: Matériau | C6: graphite pur (carbone massif) | I6: carbon_bprime/bprime_carbon_physique.md
B7: Renfort / résine | C7: sans objet — matériau monolithique | I7: aucune pyrolyse interne
B8: Système chimique | C8: C-N-O : 5 espèces d'air + 3 formes gazeuses du carbone + CO, CO2, CN + C(gr) | I8: 12 espèces au total
B9: Compositions du XML | C9: air (-bl) · pyro = C:1.0 (-py, et définit le char)
A11: §1 — HYPOTHÈSES
A12: H1 | B12: Pas de pyrolyse interne : B'g = 0. | I12: Il n'y a pas de résine à décomposer. Toute la masse injectée vient de la surface, d'où le nom de « cas dégénéré ».
A13: H2 | B13: Le char est le matériau lui-même : carbone pur, C:1.0. | I13: Aucune fermeture élémentaire à faire — c'est la seule mise en données du dépôt où la composition ne se CALCULE pas.
A14: H3 | B14: Équilibre thermochimique à la paroi, char infini. | I14: Le solveur ajoute δ = max(200, 100·B'g) de carbone élémentaire à la composition du bord de couche limite avant de normaliser, puis calcule l'équilibre multiphase.
A15: H4 | B15: C(gr) est indispensable dans la liste d'espèces. | I15: Sans phase condensée, C3 gazeux domine dès 300 K, Y_w,C → 1 et B'c ≈ 200 — non physique. C'est le contrôle du §5, valable pour TOUS les onglets carbonés.
A17: §2 — DONNÉES D'ENTRÉE
B18: bord de couche limite | C18: air : N:0.79, O:0.21 (molaire) | I18: cf. onglet Constantes §2
B19: fraction massique d'oxygène de l'air | C19: =Constantes!D19 -> 0.23290922 | I19: y_O calculé au §2 de l'onglet Constantes
B20: masse volumique du graphite [kg/m³] | C20: 1800 | I20: ordre de grandeur (1600-2200 selon la qualité) — n'entre que dans la récession
A22: §3 — CALCUL PAS À PAS
A23: > | B23: Étape 1 — composition élémentaire du char : directe | I23: le solide est du carbone pur ⇒ x_C = 1
C24: C | D24: N | E24: O | F24: Somme
B25: char (= le matériau) | C25: 1 | D25: 0 | E25: 0 | F25: =SUM(C25:E25) -> 1
A26: > | B26: Étape 2 — gaz de pyrolyse : il n'y en a pas | I26: B'g = 0 dans toutes les commandes bprime de ce matériau
B27: La composition nommée `pyro` du XML vaut néanmoins C:1.0. Ce n'est pas une incohérence : elle sert d'argument à `-py` (le parseur exige une composition valide) et définit le char. Comme elle est appelée avec -b 0.0, elle ne contribue à rien.
A28: > | B28: Étape 3 — le bilan de surface se réduit à une expression fermée | I28: B'c = [Y_e,C + B'g·Y_g,C − Y_w,C(1+B'g)] / (Y_w,C − Y_c,C)
B29: Avec Y_c,C = 1 (char de carbone pur), Y_e,C = 0 (l'air ne contient pas de carbone) et B'g = 0, il ne reste que :
B30: B'c = − Y_w,C / (Y_w,C − 1) = Y_w,C / (1 − Y_w,C)
B31: La seule inconnue est Y_w,C, la fraction massique de carbone dans le gaz d'équilibre à la paroi — c'est elle que le solveur multiphase calcule à (T_w, P).
A33: §4 — RÉSULTAT : CE QUI ENTRE DANS LE XML
B34: Composition élémentaire (fractions molaires) | C34: C | D34: N | E34: O | F34: Somme
B35: pyro / char — valeur portée dans le XML | C35: 1 | D35: — | E35: —
B36: air — valeur portée dans le XML | C36: — | D36: 0.79 | E36: 0.21 | F36: =D36+E36 -> 1
A38: §5 — CONTRÔLES ET VALIDATION CROISÉE
A39: > | B39: Contrôle de recette valable pour TOUS les matériaux carbonés du dépôt | I39: à 300 K, B'g = 0 : régime d'oxydation basse température, C(gr) + O2 → CO2
B40: À 300 K tout l'oxygène de l'air est consommé en CO2. Chaque O2 (2 atomes d'oxygène) emporte un atome de carbone : la masse de carbone ablatée par unité de masse d'air vaut donc y_O · M_C / (2·M_O). Ce nombre ne dépend PAS de la pression.
B41: B'c attendu à 300 K, 1 atm | C41: =C19*Constantes!$C$7/(2*Constantes!$C$9) -> 0.087426483 | I41: attendu 0.0874 — valeur obtenue par bprime sur carbon-air, cork-air, tacot-air…
B42: B'c obtenu si C(gr) manque dans <species> | C42: ≈ 200 | I42: signature sans ambiguïté d'une liste d'espèces incomplète : Y_w,C → 1 et B'c sature sur son plafond interne
A44: §6 — SENSIBILITÉ — régimes physiques (à 1 atm)
B45: Régime | C45: T_w [K] | D45: Phase stable | E45: Espèce gazeuse dominante | F45: Mécanisme
B46: faible ablation | C46: 300 – 700 | D46: C(gr) | E46: CO2, O2, N2 | F46: C(gr) + O2 → CO2
B47: oxydation active | C47: 700 – 3500 | D47: C(gr) | E47: CO, N2, CN | F47: C(gr) + O → CO ; Boudouard C(gr) + CO2 → 2 CO
B48: sublimation | C48: 3500 – 4000 | D48: C(gr) + gaz | E48: CO, CN, C3 | F48: C(gr) ⇌ C, C2, C3
B49: sublimation totale | C49: > 4000 | D49: gaz seul | E49: C, C2, C3 | F49: plus de phase condensée : B'c ≫ 1
B50: À haute pression les mêmes régimes sont décalés vers des températures plus élevées (la sublimation est retardée, effet Clausius-Clapeyron), tandis que les réactions d'oxydation sont favorisées. La table B' est donc une SURFACE B'c(T_w, P), tracée comme un faisceau de 25 isobares de 10⁻³ à 10³ atm.
A52: §7 — RÉPONSE MATÉRIAU (n'entre PAS dans le XML)
B53: couplage k = B'g / B'c | C53: 0 | I53: aucun gaz de pyrolyse — le graphite est le seul matériau du classeur à k = 0
B54: récession par unité de flux, B'c/ρ_c à 300 K [m³/kg] | C54: =C19*Constantes!$C$7/(2*Constantes!$C$9)/C20 -> 4.8570269e-05 | I54: ṡ = B'c·ṁe/ρ_c
A56: §8 — BLOC XML
B57: <mixture thermo_db="NASA-9">
B58: <species>
B59: N O NO N2 O2 C C2 C3 CN CO CO2 C(gr)
B60: </species>
B61: <element_compositions default="air">
B62: <composition name="air">N:0.79, O:0.21</composition>
B63: <composition name="pyro">C:1.0</composition>
B64: </element_compositions>
B65: </mixture>
B67: bprime -T 300:25:5000 -P <P> -b 0.0 -m carbon-air -bl air -py pyro

Sheet Silice
A1: Silice SiO2 — char MULTI-ÉLÉMENT
A2: Premier char du dépôt qui n'est pas du carbone (avec le SiC) : montre comment se remplit une composition à plusieurs éléments
A3: Fichier(s) XML : data/mixtures/silica-air.xml
A5: §0 — FICHE D'IDENTITÉ
B6: Matériau | C6: silice pure SiO2 | I6: silice_bprime/silice_bprime.py
B7: Système chimique | C7: Si-N-O : 5 espèces d'air + 5 espèces gazeuses du silicium + 4 phases condensées de SiO2 | I7: SiO2(a-qz), SiO2(b-qz), SiO2(b-crt), SiO2(L)
B8: Binaire dédié | C8: bprime_silica (et non bprime) | I8: le bilan est résolu sur Si, pas sur C
B9: Compositions du XML | C9: air (-bl) · silice (char, -char-elem Si)
A11: §1 — HYPOTHÈSES
A12: H1 | B12: Le char est la silice elle-même, de stœchiométrie SiO2 exacte. | I12: Matériau monolithique : pas de résine, donc pas de gaz de pyrolyse (B'g = 0) et pas de fermeture élémentaire à faire.
A13: H2 | B13: L'élément du bilan est le SILICIUM, pas le carbone. | I13: Règle générale : `-char-elem` doit désigner un élément PRÉSENT dans le char et ABSENT (ou minoritaire) au bord de couche limite. L'oxygène ne conviendrait pas — l'air en contient 21 % molaire.
A14: H3 | B14: Les quatre phases condensées de SiO2 doivent figurer dans <species>. | I14: Même exigence que C(gr) pour les matériaux carbonés : sans phase condensée, le solveur ne peut pas faire précipiter la silice et B'c sature sur une valeur non physique. Ici il faut les quatre polymorphes (quartz α et β, cristobalite β, liquide) pour couvrir toute la plage de température.
A15: H4 | B15: Équilibre thermochimique à la paroi. | I15: Identique aux autres matériaux.
A17: §2 — DONNÉES D'ENTRÉE
B18: stœchiométrie — ν_Si | C18: 1 | I18: SiO2
B19: stœchiométrie — ν_O | C19: 2
B20: masse volumique de la silice [kg/m³] | C20: 2200 | I20: silice vitreuse — n'entre que dans la récession
A22: §3 — CALCUL PAS À PAS
A23: > | B23: Étape 1 — masse molaire du motif | I23: M = ν_Si·M_Si + ν_O·M_O
B24: M(SiO2) [g/mol] | C24: =C18*Constantes!$C$11+C19*Constantes!$C$9 -> 60.0835 | I24: attendu 60.08 g/mol
A25: > | B25: Étape 2 — composition élémentaire, en molaire puis en massique | I25: x_E = ν_E / Σ ν_j ; y_E = ν_E·M_E / M
C26: Si | D26: O | E26: Somme
B27: ν_E (moles d'atomes par motif) | C27: =C18 -> 1 | D27: =C19 -> 2 | E27: =SUM(C27:D27) -> 3
B28: x_E (fraction molaire élémentaire, normalisée) | C28: =C27/$E$27 -> 0.33333333 | D28: =D27/$E$27 -> 0.66666667 | E28: =SUM(C28:D28) -> 1
B29: y_E (fraction massique élémentaire) | C29: =C27*Constantes!$C$11/$C$24 -> 0.46744114 | D29: =D27*Constantes!$C$9/$C$24 -> 0.53255886 | E29: =SUM(C29:D29) -> 1
B30: Attendu : x_Si = 0.3333 / x_O = 0.6667 en molaire, y_Si = 0.4674 / y_O = 0.5326 en masse. Le piège classique est de confondre les deux — le parseur suppose du MOLAIRE par défaut.
A32: §4 — RÉSULTAT : CE QUI ENTRE DANS LE XML
B33: Composition élémentaire | C33: Si | D33: O | E33: Somme | F33: après normalisation par le parseur
B34: valeur portée dans le XML (silice) | C34: 1 | D34: 2 | E34: =SUM(C34:D34) -> 3 | F34: x_Si = 1/3, x_O = 2/3
B35: C'est l'illustration la plus nette de la règle de normalisation automatique (Composition::componentsFromList) : « Si:1.0, O:2.0 » somme à 3, et le parseur le ramène à 1. On peut donc saisir indifféremment des moles brutes, des pourcentages ou des fractions — c'est le RAPPORT qui compte, et écrire directement Si:0.3333, O:0.6667 donnerait exactement le même mélange.
A37: §5 — CONTRÔLES ET VALIDATION CROISÉE
B38: x_Si + x_O après normalisation | C38: =C28+D28 -> 1 | I38: doit valoir 1 exactement
B39: rapport O/Si | C39: =D27/C27 -> 2 | I39: doit valoir 2 — la stœchiométrie de la silice
B40: Le cas de la silice est aussi le CONTRE-EXEMPLE de référence pour les composites : dès que les constituants ne carbonisent pas vers le même produit (fibres de silice + résine phénolique, par exemple), le char devient multi-élément et il faut pondérer par les MASSES de char de chaque constituant : n_E(char) = Σ_i (m_char,i / M_i)·ν_E,i. Le ratio renfort/résine entre alors dans la table B' — cf. onglet CPh70 §6 pour le cas contraire, et l'onglet Liège-phénolique §5 pour un exemple chiffré de pondération.
A42: §6 — SENSIBILITÉ
B43: Sans objet : la stœchiométrie SiO2 est exacte, il n'y a ni rendement en char, ni analyse élémentaire, ni motif de résine à choisir. C'est la mise en données la moins incertaine du classeur — l'incertitude est reportée sur la base thermodynamique des quatre phases condensées et sur l'hypothèse d'équilibre à la paroi.
A45: §7 — RÉPONSE MATÉRIAU (n'entre PAS dans le XML)
B46: couplage k = B'g / B'c | C46: 0 | I46: pas de pyrolyse interne — comme le graphite
B47: ρ_char [kg/m³] | C47: =C20 -> 2200 | I47: la silice fondue est évacuée mécaniquement : la récession réelle dépasse celle donnée par B'c seul
A49: §8 — BLOC XML
B50: <mixture thermo_db="NASA-9">
B51: <species>
B52: N O NO N2 O2 Si SiO SiO2 Si2 SiN SiO2(a-qz) SiO2(b-qz) SiO2(b-crt) SiO2(L)
B53: </species>
B54: <element_compositions default="air">
B55: <composition name="air">N:0.79, O:0.21</composition>
B56: <composition name="silice">Si:1.0, O:2.0</composition>
B57: </element_compositions>
B58: </mixture>
B60: bprime_silica -T 300:25:5000 -P <P> -b 0.0 -m silica-air -bl air

Sheet SiC
A1: Carbure de silicium SiC — char multi-élément NON congruent
A2: Char à deux éléments qui peut laisser à la paroi SiO2, Si liquide ou carbone : le bilan est suivi sur l'azote de l'air
A3: Fichier(s) XML : data/mixtures/sic-air.xml
A5: §0 — FICHE D'IDENTITÉ
B6: Matériau | C6: carbure de silicium massif β-SiC (dense, fritté ou CVD) | I6: sic_bprime/sic_bprime.py · sic_bprime/README.md
B7: Système chimique | C7: Si-C-N-O : 5 espèces d'air + 6 gaz carbonés + 10 gaz siliciés (SiO, SiO2, SiC, SiC2, Si2C, SiN…) + 9 phases condensées | I7: 30 espèces au total
B8: Phases condensées | C8: C(gr) · Si(cr), Si(L) · SiC(b), SiC(L) · SiO2(a-qz), SiO2(b-qz), SiO2(b-crt), SiO2(L) | I8: une seule forme de chaque famille est valide à une température donnée
B9: Binaire | C9: bprime généralisé : -char sic -char-elem N | I9: aucun binaire dédié (contrairement à bprime_silica)
B10: Compositions du XML | C10: air (-bl) · sic (char, -char)
A12: §1 — HYPOTHÈSES
A13: H1 | B13: Le char est le SiC lui-même, de stœchiométrie Si:C = 1:1 exacte. | I13: Matériau monolithique : pas de résine, donc pas de gaz de pyrolyse (B'g = 0) et pas de fermeture élémentaire à faire.
A14: H2 | B14: L'élément du bilan est l'AZOTE de l'air, pas Si ni C. | I14: Le SiC ne se consomme pas toujours en bloc : selon (T_w, P) il laisse de la silice (oxydation passive), du silicium liquide ou un résidu de carbone (décomposition SiC → Si(g) + C(gr)). Suivre Si ou C donne alors un B'c faux — nul, ou négatif puis écrêté, alors que le matériau se décompose (§5). N est inerte et absent de toute phase condensée : son bilan donne la masse NETTE gazéifiée par la paroi. Pour le carbone et la silice, dont le char est la seule phase condensée, le résultat est identique à celui du suivi sur C ou sur Si.
A15: H3 | B15: Toutes les phases condensées du système Si-C-O figurent dans <species>, sauf Si3N4. | I15: Même exigence que C(gr) pour le carbone : sans SiO2 condensée, l'oxydation passive disparaît ; sans C(gr), le résidu de décomposition ne peut pas se former. Si3N4(cr) est écarté : il bloque le solveur, et la nitruration du SiC sous air est cinétiquement inhibée.
A16: H4 | B16: Équilibre thermochimique à la paroi, vérifié point par point. | I16: Le solveur multiphase boucle sur ~7 % des points (frontières de phases). Chaque point est contrôlé : aucune phase absente ne doit avoir une force motrice g°/RT − Σ a·λ négative. Sinon les assemblages de phases sont énumérés et celui qui vérifie ce critère est retenu (équilibre vrai). Là où plusieurs solides coexistent (SiC + C(gr), SiC + SiO2 + Si(L)), l'équilibre à assemblage fixé est résolu directement en potentiels élémentaires. Bilan : 4387 points directs, 289 par énumération, 49 à assemblage fixé, tous strictement stables.
A18: §2 — DONNÉES D'ENTRÉE
B19: stœchiométrie — ν_Si | C19: 1 | I19: SiC
B20: stœchiométrie — ν_C | C20: 1
B21: fraction massique d'oxygène de l'air | C21: =Constantes!D19 -> 0.23290922 | I21: y_O calculé au §2 de l'onglet Constantes
B22: fraction massique d'azote de l'air | C22: =Constantes!C19 -> 0.76709078 | I22: y_N — l'élément de suivi du bilan (H2)
B23: masse volumique du SiC [kg/m³] | C23: 3210 | I23: β-SiC dense — n'entre que dans la récession
A25: §3 — CALCUL PAS À PAS
A26: > | B26: Étape 1 — masse molaire du motif | I26: M = ν_Si·M_Si + ν_C·M_C
B27: M(SiC) [g/mol] | C27: =C19*Constantes!$C$11+C20*Constantes!$C$7 -> 40.0965 | I27: attendu 40.10 g/mol
A28: > | B28: Étape 2 — composition élémentaire, en molaire puis en massique | I28: x_E = ν_E / Σ ν_j ; y_E = ν_E·M_E / M
C29: Si | D29: C | E29: Somme
B30: ν_E (moles d'atomes par motif) | C30: =C19 -> 1 | D30: =C20 -> 1 | E30: =SUM(C30:D30) -> 2
B31: x_E (fraction molaire élémentaire, normalisée) | C31: =C30/$E$30 -> 0.5 | D31: =D30/$E$30 -> 0.5 | E31: =SUM(C31:D31) -> 1
B32: y_E (fraction massique élémentaire) | C32: =C30*Constantes!$C$11/$C$27 -> 0.70044767 | D32: =D30*Constantes!$C$7/$C$27 -> 0.29955233 | E32: =SUM(C32:D32) -> 1
B33: Attendu : x_Si = x_C = 0.5000 en molaire, y_Si = 0.7005 / y_C = 0.2995 en masse.
A34: > | B34: Étape 3 — le bilan de surface, écrit sur l'azote | I34: B'c = [Y_e,N + B'g·Y_g,N − Y_w,N(1+B'g)] / (Y_w,N − Y_c,N)
B35: Avec Y_c,N = 0 (le char ne contient pas d'azote) et B'g = 0, il ne reste que :
B36: B'c = Y_e,N / Y_w,N − 1 (masse nette gazéifiée par unité de masse d'air)
B37: Le gaz à la paroi contient (1 + B'c) fois la masse d'air qui y entre ; l'azote, qui ne se dépose nulle part, s'y trouve dilué d'autant. Si la paroi FIXE de l'oxygène (silice d'oxydation passive), la masse gazéifiée nette est négative : bprime écrête B'c à 0, comme pour tous les matériaux.
A39: §4 — RÉSULTAT : CE QUI ENTRE DANS LE XML
B40: Composition élémentaire | C40: Si | D40: C | E40: Somme | F40: après normalisation par le parseur
B41: valeur portée dans le XML (sic) | C41: 1 | D41: 1 | E41: =SUM(C41:D41) -> 2 | F41: x_Si = x_C = 1/2
B42: air — valeur portée dans le XML | C42: N : 0.79 | D42: O : 0.21
A44: §5 — CONTRÔLES ET VALIDATION CROISÉE
A45: > | B45: Contrôle 1 — plateau d'oxydation ACTIVE, indépendant de la pression | I45: SiC + O2 → SiO(g) + CO : un SiC gazéifié par O2 consommé
B46: Tout l'oxygène de l'air part en SiO et CO, la paroi reste du SiC nu. Chaque O2 (2 atomes d'oxygène) emporte un motif SiC : la masse ablatée par unité de masse d'air vaut y_O · M_SiC / (2·M_O).
B47: B'c attendu sur le plateau | C47: =C21*$C$27/(2*Constantes!$C$9) -> 0.29185713 | I47: table : 0.2920 à 1 atm entre 1975 et 2200 K ; 0.2919 à 0.001 atm, 1600 K
A48: > | B48: Contrôle 2 — oxydation PASSIVE à basse température | I48: SiC + O2 → SiO2(s) + C(gr) : la paroi fixe l'oxygène
B49: Le gaz à la paroi est de l'azote pur : Y_w,N = 1, donc B'c = Y_e,N − 1 < 0 (prise de masse), écrêté à 0. C'est la couche de silice protectrice qui fait l'intérêt du SiC.
B50: B'c brut (avant écrêtage) à 300 K | C50: =C22/1-1 -> -0.23290922 | I50: prise de masse = masse d'oxygène fixée
A51: > | B51: Contrôle 3 — pourquoi PAS -char-elem Si : comparaison sur trois points calculés
B52: Point (T_w, P) | C52: phases à la paroi | D52: B'c suivi N | E52: B'c suivi Si | F52: B'c suivi C
B53: 2100 K, 1 atm | C53: SiC | D53: 0.292 | E53: 0.292 | F53: 0.292
B54: 2600 K, 1 atm | C54: SiC + Si(L) | D54: 0.2583 | E54: 0.1506 | F54: 0.6108
B55: 2500 K, 0.001 atm | C55: C(gr) (résidu) | D55: 185.4 | E55: 0 | F55: 4.312
B56: Les trois suivis coïncident tant que le SiC est la seule phase condensée. Dès qu'un autre solide reste à la paroi, un suivi sur un seul élément du char suppose à tort que l'autre part avec lui dans le rapport 1:1 : avec Si liquide résiduel, le suivi sur Si sous-estime (0.15) et le suivi sur C surestime (0.61) ; avec un résidu de carbone, le suivi sur Si tombe à 0 alors que le SiC se décompose. Le suivi sur N donne la masse réellement injectée dans la couche limite, celle qu'attend le bilan d'énergie de surface.
A58: §6 — SENSIBILITÉ — régimes physiques (à 1 atm)
B59: Régime | C59: T_w [K] | D59: Phases condensées | E59: Espèces gazeuses dominantes | F59: Mécanisme
B60: oxydation passive | C60: 300 – 1625 | D60: SiC + SiO2 + C(gr) | E60: N2 | F60: SiC + O2 → SiO2 + C ; B'c = 0
B61: transition passive → active | C61: 1650 – 1950 | D61: SiC + SiO2 | E61: N2, CO, SiO | F61: SiC + 2 SiO2 → 3 SiO + CO ; B'c 0 → 0.17
B62: oxydation active | C62: 1975 – 2200 | D62: SiC | E62: N2, CO, SiO | F62: SiC + O2 → SiO + CO ; B'c = 0.292
B63: oxydation + silicium liquide | C63: 2225 – 3000 | D63: SiC + Si(L) | E63: N2, CO, SiO, Si, Si2C | F63: SiC + O → Si(L) + CO ; B'c 0.29 → 1.7
B64: sublimation | C64: 3025 – 3100 | D64: SiC | E64: SiC2, Si2C, Si | F64: SiC ⇌ Si + SiC2 + Si2C ; B'c 2.3 → 13.5
B65: sublimation totale | C65: ≥ 3125 | D65: gaz seul | E65: Si, SiC2, Si2C | F65: plus de phase condensée : B'c = 200 (plafond)
B66: La pression décale TOUTES les transitions : à 0.001 atm l'oxydation devient active dès 1500 K et le SiC se décompose en laissant un résidu de carbone dès 2350 K ; à 1000 atm la silice (liquide) protège jusqu'à ~2700 K. Assemblage retenu en chaque point : sic_bprime/sic_bprime_phases.csv.
A68: §7 — RÉPONSE MATÉRIAU (n'entre PAS dans le XML)
B69: couplage k = B'g / B'c | C69: 0 | I69: pas de pyrolyse interne — comme le graphite et la silice
B70: récession par unité de flux sur le plateau actif, B'c/ρ [m³/kg] | C70: =C21*$C$27/(2*Constantes!$C$9)/C23 -> 9.0921224e-05 | I70: ṡ = B'c·ṁe/ρ — valable tant que la paroi reste du SiC nu
B71: Hors du régime actif la paroi porte un autre solide (SiO2, Si liquide, carbone) : B'c reste la masse gazéifiée, mais la récession du SiC n'en découle plus directement — le solide résiduel s'accumule, coule ou s'écaille, ce que le modèle d'équilibre ne décrit pas.
A73: §8 — BLOC XML
B74: <mixture thermo_db="NASA-9">
B75: <species>
B76: N O NO N2 O2
B77: C C2 C3 CN CO CO2
B78: Si Si2 Si3 SiO SiO2 SiN Si2N SiC SiC2 Si2C
B79: C(gr) Si(cr) Si(L) SiC(b) SiC(L)
B80: SiO2(a-qz) SiO2(b-qz) SiO2(b-crt) SiO2(L)
B81: </species>
B82: <element_compositions default="air">
B83: <composition name="air">N:0.79, O:0.21</composition>
B84: <composition name="sic">Si:1.0, C:1.0</composition>
B85: </element_compositions>
... B88: bprime -T <Tw> -P <P> -b 0.0 -m sic-air -bl air -char sic -char-elem N (point par point, cf. sic_bprime.py)

Sheet Molybdène
A1: Molybdène Mo (TZM) — métal à oxyde VOLATIL
A2: Char monoélément dont l'oxyde MoO3 s'évapore : deux tables encadrent la réalité, équilibre complet (borne basse) et surface nue (borne haute)
A3: Fichier(s) XML : data/mixtures/mo-air.xml
A5: §0 — FICHE D'IDENTITÉ
B6: Matériau | C6: molybdène ; s'applique au TZM (Mo + 0.5 % Ti, 0.08 % Zr, ~0.02 % C) | I6: mo_bprime/mo_bprime.py · mo_bprime/README.md
B7: Système chimique | C7: Mo-N-O : 5 espèces d'air + Mo, MoO, MoO2, MoO3 et polymères Mo2O6…Mo5O15 + 5 phases condensées | I7: 18 espèces au total
B8: Phases condensées | C8: Mo(cr), Mo(L) · MoO2(cr) · MoO3(cr), MoO3(L) | I8: toutes présentes dans nasa9.dat
B9: Binaire | C9: bprime généralisé : -char mo -char-elem N
B10: Compositions du XML | C10: air (-bl) · mo (char, -char)
A12: §1 — HYPOTHÈSES
A13: H1 | B13: Le char est le métal pur, Mo:1.0 ; les additions du TZM sont ignorées. | I13: Ti, Zr et C durcissent l'alliage mais ne changent pas son oxydation, et n'ont pas de données dans la base. Pas de pyrolyse : B'g = 0.
A14: H2 | B14: Bilan suivi sur N, comme pour le SiC. | I14: B'c = masse nette gazéifiée. Pour un char monoélément, identique au suivi sur Mo tant que seul le métal est condensé.
A15: H3 | B15: L'équilibre complet est une BORNE BASSE. | I15: Avec un excès de métal, l'oxygène est fixé en MoO2 solide et B'c = 0 jusqu'à ~2350 K à 1 atm. En réalité MoO3 se forme sur la face externe de l'oxyde, fond à 795 °C et s'évapore : le molybdène s'oxyde vite dès ~1000 K.
A16: H4 | B16: La table « surface nue » (sans oxydes condensés) est une BORNE HAUTE. | I16: Tout l'oxygène qui atteint la paroi repart en oxydes gazeux : régime limité par la diffusion dans la couche limite. Conservative au-dessus de ~1000 K, fausse en dessous (cinétique lente).
A18: §2 — DONNÉES D'ENTRÉE
B19: M_Mo [g/mol] | C19: 95.96 | I19: data/thermo/elements.xml (masse de Mutation++)
B20: fraction massique d'oxygène de l'air | C20: =Constantes!D19 -> 0.23290922 | I20: y_O calculé au §2 de l'onglet Constantes
B21: masse volumique du TZM [kg/m³] | C21: 10220 | I21: Mo pur : 10 280 kg/m³ — n'entre que dans la récession
A23: §3 — CALCUL PAS À PAS
A24: > | B24: Étape 1 — composition élémentaire du char : directe | I24: métal pur ⇒ x_Mo = y_Mo = 1
A25: > | B25: Étape 2 — réaction limite du régime de diffusion | I25: Mo + 3/2 O2 → MoO3(g)
B26: Chaque molécule d'O2 qui atteint la paroi emporte 2/3 d'atome de molybdène. La masse de Mo gazéifiée par unité de masse d'air vaut donc y_O · M_Mo / (3·M_O), indépendamment de la pression.
B27: B'c limite de diffusion (MoO3) | C27: =C20*C19/(3*Constantes!$C$9) -> 0.46565345 | I27: table « surface nue » : 0.4657 sur tout le plateau
B28: B'c si l'oxyde gazeux était MoO2 | C28: =C20*C19/(2*Constantes!$C$9) -> 0.69848017 | I28: borne supérieure du plateau, approchée à haute T quand MoO2 et MoO remplacent MoO3
A30: §4 — RÉSULTAT : CE QUI ENTRE DANS LE XML
B31: Composition élémentaire | C31: Mo | D31: N | E31: O
B32: mo — valeur portée dans le XML | C32: 1 | D32: — | E32: —
B33: air — valeur portée dans le XML | C33: — | D33: 0.79 | E33: 0.21
B34: La variante « surface nue » n'est pas un fichier du dépôt : mo_bprime.py l'écrit à la volée en retirant MoO2(cr), MoO3(cr) et MoO3(L) de la liste d'espèces.
A36: §5 — CONTRÔLES ET VALIDATION CROISÉE
B37: plateau de la table « surface nue » | C37: 0.4657 | I37: à comparer au calcul analytique du §3
B38: écart relatif | C38: =ABS(C37-C27)/C27 -> 9.9970821e-05 | I38: l'arrondi de la table
B39: points instables (critère de force motrice) | C39: 0 | I39: table d'équilibre complet, 4725 points — contrôle du script SiC
A41: §6 — SENSIBILITÉ — disparition des oxydes condensés (équilibre complet)
B42: P [atm] | C42: T_w [K]
B43: 0.001 | C43: 1875
B44: 0.01 | C44: 2025
B45: 0.1 | C45: 2175
B46: 1 | C46: 2350
B47: 10 | C47: 2600
B48: 100 | C48: 2925
B49: 1000 | C49: 4775
B50: En dessous de ces températures, l'équilibre complet donne B'c = 0 (MoO2 solide) et la surface nue 0.466 : la vérité est entre les deux, fixée par la cinétique. Au-dessus, les deux tables coïncident ; fusion du métal à 2896 K, puis sublimation jusqu'au plafond B'c = 200.
A52: §7 — RÉPONSE MATÉRIAU (n'entre PAS dans le XML)
B53: couplage k = B'g / B'c | C53: 0 | I53: pas de pyrolyse interne
B54: récession par unité de flux en limite de diffusion, B'c/ρ [m³/kg] | C54: =C27/C21 -> 4.556296e-05 | I54: ṡ = B'c·ṁe/ρ — borne haute au-dessus de ~1000 K
B55: Dans l'air, le TZM s'emploie revêtu (siliciures de type MoSi2). La table décrit le métal mis à nu par une défaillance du revêtement.
A57: §8 — BLOC XML
B58: <mixture thermo_db="NASA-9">
B59: <species>
B60: N O NO N2 O2
B61: Mo MoO MoO2 MoO3 Mo2O6 Mo3O9 Mo4O12 Mo5O15
B62: Mo(cr) Mo(L) MoO2(cr) MoO3(cr) MoO3(L)
B63: </species>
B64: <element_compositions default="air">
B65: <composition name="air">N:0.79, O:0.21</composition>
B66: <composition name="mo">Mo:1.0</composition>
B67: </element_compositions>
B68: </mixture>
B70: bprime -T 300:25:5000 -P <P> -b 0.0 -m mo-air -bl air -char mo -char-elem N
